<?xml version="1.0" encoding="UTF-8" standalone="yes"?>
<?mso-application progid="Word.Document"?>
<w:wordDocument xmlns:aml="http://schemas.microsoft.com/aml/2001/core" xmlns:wpc="http://schemas.microsoft.com/office/word/2010/wordprocessingCanvas" xmlns:cx="http://schemas.microsoft.com/office/drawing/2014/chartex" xmlns:cx1="http://schemas.microsoft.com/office/drawing/2015/9/8/chartex" xmlns:dt="uuid:C2F41010-65B3-11d1-A29F-00AA00C14882" xmlns:mc="http://schemas.openxmlformats.org/markup-compatibility/2006" xmlns:o="urn:schemas-microsoft-com:office:office" xmlns:v="urn:schemas-microsoft-com:vml" xmlns:w10="urn:schemas-microsoft-com:office:word" xmlns:w="http://schemas.microsoft.com/office/word/2003/wordml" xmlns:wx="http://schemas.microsoft.com/office/word/2003/auxHint" xmlns:wne="http://schemas.microsoft.com/office/word/2006/wordml" xmlns:wsp="http://schemas.microsoft.com/office/word/2003/wordml/sp2" xmlns:sl="http://schemas.microsoft.com/schemaLibrary/2003/core" xmlns:ns0="http://schemas.microsoft.com/office/drawing/2015/10/21/chartex" xmlns:ns1="http://schemas.microsoft.com/office/drawing/2016/5/9/chartex" xmlns:ns2="http://schemas.microsoft.com/office/drawing/2016/5/10/chartex" xmlns:ns3="http://schemas.microsoft.com/office/drawing/2016/5/11/chartex" xmlns:ns4="http://schemas.microsoft.com/office/drawing/2016/5/12/chartex" xmlns:ns5="http://schemas.microsoft.com/office/drawing/2016/5/13/chartex" xmlns:ns6="http://schemas.microsoft.com/office/drawing/2016/5/14/chartex" xmlns:ns7="http://schemas.microsoft.com/office/drawing/2016/ink" xmlns:ns8="http://schemas.microsoft.com/office/drawing/2017/model3d" w:macrosPresent="no" w:embeddedObjPresent="no" w:ocxPresent="no" xml:space="preserve"><w:ignoreSubtree w:val="http://schemas.microsoft.com/office/word/2003/wordml/sp2"/><o:DocumentProperties><o:Author>VU VAN GIANG</o:Author><o:LastAuthor>Nguyen Tien Nam</o:LastAuthor><o:Revision>47</o:Revision><o:TotalTime>28</o:TotalTime><o:Created>2021-09-03T10:06:00Z</o:Created><o:LastSaved>2021-12-27T04:26:00Z</o:LastSaved><o:Pages>1</o:Pages><o:Words>118</o:Words><o:Characters>678</o:Characters><o:Lines>5</o:Lines><o:Paragraphs>1</o:Paragraphs><o:CharactersWithSpaces>795</o:CharactersWithSpaces><o:Version>16</o:Version></o:DocumentProperties><w:fonts><w:defaultFonts w:ascii="Calibri" w:fareast="Calibri" w:h-ansi="Calibri" w:cs="Times New Roman"/><w:font w:name="Times New Roman"><w:panose-1 w:val="02020603050405020304"/><w:charset w:val="00"/><w:family w:val="Roman"/><w:pitch w:val="variable"/><w:sig w:usb-0="E0002EFF" w:usb-1="C000785B" w:usb-2="00000009" w:usb-3="00000000" w:csb-0="000001FF" w:csb-1="00000000"/></w:font><w:font w:name="Times New Roman"><w:panose-1 w:val="02020603050405020304"/><w:charset w:val="00"/><w:family w:val="Roman"/><w:pitch w:val="variable"/><w:sig w:usb-0="E0002EFF" w:usb-1="C000785B" w:usb-2="00000009" w:usb-3="00000000" w:csb-0="000001FF" w:csb-1="00000000"/></w:font><w:font w:name="Calibri"><w:panose-1 w:val="020F0502020204030204"/><w:charset w:val="00"/><w:family w:val="Swiss"/><w:pitch w:val="variable"/><w:sig w:usb-0="E4002EFF" w:usb-1="C000247B" w:usb-2="00000009" w:usb-3="00000000" w:csb-0="000001FF" w:csb-1="00000000"/></w:font></w:fonts><w:styles><w:versionOfBuiltInStylenames w:val="7"/><w:latentStyles w:defLockedState="off" w:latentStyleCount="371"><w:lsdException w:name="Normal"/><w:lsdException w:name="heading 1"/><w:lsdException w:name="heading 2"/><w:lsdException w:name="heading 3"/><w:lsdException w:name="heading 4"/><w:lsdException w:name="heading 5"/><w:lsdException w:name="heading 6"/><w:lsdException w:name="heading 7"/><w:lsdException w:name="heading 8"/><w:lsdException w:name="heading 9"/><w:lsdException w:name="caption"/><w:lsdException w:name="Title"/><w:lsdException w:name="Subtitle"/><w:lsdException w:name="Strong"/><w:lsdException w:name="Emphasis"/><w:lsdException w:name="Normal Table"/><w:lsdException w:name="Table Simple 1"/><w:lsdException w:name="Table Simple 2"/><w:lsdException w:name="Table Simple 3"/><w:lsdException w:name="Table Classic 1"/><w:lsdException w:name="Table Classic 2"/><w:lsdException w:name="Table Classic 3"/><w:lsdException w:name="Table Classic 4"/><w:lsdException w:name="Table Colorful 1"/><w:lsdException w:name="Table Colorful 2"/><w:lsdException w:name="Table Colorful 3"/><w:lsdException w:name="Table Columns 1"/><w:lsdException w:name="Table Columns 2"/><w:lsdException w:name="Table Columns 3"/><w:lsdException w:name="Table Columns 4"/><w:lsdException w:name="Table Columns 5"/><w:lsdException w:name="Table Grid 1"/><w:lsdException w:name="Table Grid 2"/><w:lsdException w:name="Table Grid 3"/><w:lsdException w:name="Table Grid 4"/><w:lsdException w:name="Table Grid 5"/><w:lsdException w:name="Table Grid 6"/><w:lsdException w:name="Table Grid 7"/><w:lsdException w:name="Table Grid 8"/><w:lsdException w:name="Table List 1"/><w:lsdException w:name="Table List 2"/><w:lsdException w:name="Table List 3"/><w:lsdException w:name="Table List 4"/><w:lsdException w:name="Table List 5"/><w:lsdException w:name="Table List 6"/><w:lsdException w:name="Table List 7"/><w:lsdException w:name="Table List 8"/><w:lsdException w:name="Table 3D effects 1"/><w:lsdException w:name="Table 3D effects 2"/><w:lsdException w:name="Table 3D effects 3"/><w:lsdException w:name="Table Contemporary"/><w:lsdException w:name="Table Elegant"/><w:lsdException w:name="Table Professional"/><w:lsdException w:name="Table Subtle 1"/><w:lsdException w:name="Table Subtle 2"/><w:lsdException w:name="Table Web 1"/><w:lsdException w:name="Table Web 2"/><w:lsdException w:name="Table Web 3"/><w:lsdException w:name="Table Theme"/><w:lsdException w:name="No Spacing"/><w:lsdException w:name="Light Shading"/><w:lsdException w:name="Light List"/><w:lsdException w:name="Light Grid"/><w:lsdException w:name="Medium Shading 1"/><w:lsdException w:name="Medium Shading 2"/><w:lsdException w:name="Medium List 1"/><w:lsdException w:name="Medium List 2"/><w:lsdException w:name="Medium Grid 1"/><w:lsdException w:name="Medium Grid 2"/><w:lsdException w:name="Medium Grid 3"/><w:lsdException w:name="Dark List"/><w:lsdException w:name="Colorful Shading"/><w:lsdException w:name="Colorful List"/><w:lsdException w:name="Colorful Grid"/><w:lsdException w:name="Light Shading Accent 1"/><w:lsdException w:name="Light List Accent 1"/><w:lsdException w:name="Light Grid Accent 1"/><w:lsdException w:name="Medium Shading 1 Accent 1"/><w:lsdException w:name="Medium Shading 2 Accent 1"/><w:lsdException w:name="Medium List 1 Accent 1"/><w:lsdException w:name="List Paragraph"/><w:lsdException w:name="Quote"/><w:lsdException w:name="Intense Quote"/><w:lsdException w:name="Medium List 2 Accent 1"/><w:lsdException w:name="Medium Grid 1 Accent 1"/><w:lsdException w:name="Medium Grid 2 Accent 1"/><w:lsdException w:name="Medium Grid 3 Accent 1"/><w:lsdException w:name="Dark List Accent 1"/><w:lsdException w:name="Colorful Shading Accent 1"/><w:lsdException w:name="Colorful List Accent 1"/><w:lsdException w:name="Colorful Grid Accent 1"/><w:lsdException w:name="Light Shading Accent 2"/><w:lsdException w:name="Light List Accent 2"/><w:lsdException w:name="Light Grid Accent 2"/><w:lsdException w:name="Medium Shading 1 Accent 2"/><w:lsdException w:name="Medium Shading 2 Accent 2"/><w:lsdException w:name="Medium List 1 Accent 2"/><w:lsdException w:name="Medium List 2 Accent 2"/><w:lsdException w:name="Medium Grid 1 Accent 2"/><w:lsdException w:name="Medium Grid 2 Accent 2"/><w:lsdException w:name="Medium Grid 3 Accent 2"/><w:lsdException w:name="Dark List Accent 2"/><w:lsdException w:name="Colorful Shading Accent 2"/><w:lsdException w:name="Colorful List Accent 2"/><w:lsdException w:name="Colorful Grid Accent 2"/><w:lsdException w:name="Light Shading Accent 3"/><w:lsdException w:name="Light List Accent 3"/><w:lsdException w:name="Light Grid Accent 3"/><w:lsdException w:name="Medium Shading 1 Accent 3"/><w:lsdException w:name="Medium Shading 2 Accent 3"/><w:lsdException w:name="Medium List 1 Accent 3"/><w:lsdException w:name="Medium List 2 Accent 3"/><w:lsdException w:name="Medium Grid 1 Accent 3"/><w:lsdException w:name="Medium Grid 2 Accent 3"/><w:lsdException w:name="Medium Grid 3 Accent 3"/><w:lsdException w:name="Dark List Accent 3"/><w:lsdException w:name="Colorful Shading Accent 3"/><w:lsdException w:name="Colorful List Accent 3"/><w:lsdException w:name="Colorful Grid Accent 3"/><w:lsdException w:name="Light Shading Accent 4"/><w:lsdException w:name="Light List Accent 4"/><w:lsdException w:name="Light Grid Accent 4"/><w:lsdException w:name="Medium Shading 1 Accent 4"/><w:lsdException w:name="Medium Shading 2 Accent 4"/><w:lsdException w:name="Medium List 1 Accent 4"/><w:lsdException w:name="Medium List 2 Accent 4"/><w:lsdException w:name="Medium Grid 1 Accent 4"/><w:lsdException w:name="Medium Grid 2 Accent 4"/><w:lsdException w:name="Medium Grid 3 Accent 4"/><w:lsdException w:name="Dark List Accent 4"/><w:lsdException w:name="Colorful Shading Accent 4"/><w:lsdException w:name="Colorful List Accent 4"/><w:lsdException w:name="Colorful Grid Accent 4"/><w:lsdException w:name="Light Shading Accent 5"/><w:lsdException w:name="Light List Accent 5"/><w:lsdException w:name="Light Grid Accent 5"/><w:lsdException w:name="Medium Shading 1 Accent 5"/><w:lsdException w:name="Medium Shading 2 Accent 5"/><w:lsdException w:name="Medium List 1 Accent 5"/><w:lsdException w:name="Medium List 2 Accent 5"/><w:lsdException w:name="Medium Grid 1 Accent 5"/><w:lsdException w:name="Medium Grid 2 Accent 5"/><w:lsdException w:name="Medium Grid 3 Accent 5"/><w:lsdException w:name="Dark List Accent 5"/><w:lsdException w:name="Colorful Shading Accent 5"/><w:lsdException w:name="Colorful List Accent 5"/><w:lsdException w:name="Colorful Grid Accent 5"/><w:lsdException w:name="Light Shading Accent 6"/><w:lsdException w:name="Light List Accent 6"/><w:lsdException w:name="Light Grid Accent 6"/><w:lsdException w:name="Medium Shading 1 Accent 6"/><w:lsdException w:name="Medium Shading 2 Accent 6"/><w:lsdException w:name="Medium List 1 Accent 6"/><w:lsdException w:name="Medium List 2 Accent 6"/><w:lsdException w:name="Medium Grid 1 Accent 6"/><w:lsdException w:name="Medium Grid 2 Accent 6"/><w:lsdException w:name="Medium Grid 3 Accent 6"/><w:lsdException w:name="Dark List Accent 6"/><w:lsdException w:name="Colorful Shading Accent 6"/><w:lsdException w:name="Colorful List Accent 6"/><w:lsdException w:name="Colorful Grid Accent 6"/><w:lsdException w:name="Subtle Emphasis"/><w:lsdException w:name="Intense Emphasis"/><w:lsdException w:name="Subtle Reference"/><w:lsdException w:name="Intense Reference"/><w:lsdException w:name="Book Title"/><w:lsdException w:name="TOC Heading"/></w:latentStyles><w:style w:type="paragraph" w:default="on" w:styleId="Normal"><w:name w:val="Normal"/><w:rsid w:val="00011173"/><w:pPr><w:spacing w:after="160" w:line="259" w:line-rule="auto"/></w:pPr><w:rPr><w:rFonts w:ascii="Times New Roman" w:h-ansi="Times New Roman"/><wx:font wx:val="Times New Roman"/><w:sz w:val="22"/><w:sz-cs w:val="22"/><w:lang w:val="VI" w:fareast="VI" w:bidi="AR-SA"/></w:rPr></w:style><w:style w:type="character" w:default="on" w:styleId="DefaultParagraphFont"><w:name w:val="Default Paragraph Font"/></w:style><w:style w:type="table" w:default="on" w:styleId="TableNormal"><w:name w:val="Normal Table"/><wx:uiName wx:val="Table Normal"/><w:rPr><wx:font wx:val="Calibri"/><w:lang w:val="EN-US" w:fareast="EN-US" w:bidi="AR-SA"/></w:rPr><w:tblPr><w:tblInd w:w="0" w:type="dxa"/><w:tblCellMar><w:top w:w="0" w:type="dxa"/><w:left w:w="108" w:type="dxa"/><w:bottom w:w="0" w:type="dxa"/><w:right w:w="108" w:type="dxa"/></w:tblCellMar></w:tblPr></w:style><w:style w:type="list" w:default="on" w:styleId="NoList"><w:name w:val="No List"/></w:style><w:style w:type="table" w:styleId="TableGrid"><w:name w:val="Table Grid"/><w:basedOn w:val="TableNormal"/><w:rsid w:val="004531CA"/><w:rPr><wx:font wx:val="Calibri"/></w:rPr><w:tblPr><w:tblBorders><w:top w:val="single" w:sz="4" wx:bdrwidth="10" w:space="0" w:color="auto"/><w:left w:val="single" w:sz="4" wx:bdrwidth="10" w:space="0" w:color="auto"/><w:bottom w:val="single" w:sz="4" wx:bdrwidth="10" w:space="0" w:color="auto"/><w:right w:val="single" w:sz="4" wx:bdrwidth="10" w:space="0" w:color="auto"/><w:insideH w:val="single" w:sz="4" wx:bdrwidth="10" w:space="0" w:color="auto"/><w:insideV w:val="single" w:sz="4" wx:bdrwidth="10" w:space="0" w:color="auto"/></w:tblBorders></w:tblPr></w:style><w:style w:type="paragraph" w:styleId="NormalWeb"><w:name w:val="Normal (Web)"/><w:basedOn w:val="Normal"/><w:rsid w:val="004531CA"/><w:pPr><w:spacing w:before="100" w:before-autospacing="on" w:after="100" w:after-autospacing="on" w:line="240" w:line-rule="auto"/></w:pPr><w:rPr><w:rFonts w:fareast="Times New Roman"/><wx:font wx:val="Times New Roman"/><w:sz w:val="24"/><w:sz-cs w:val="24"/></w:rPr></w:style></w:styles><w:shapeDefaults><o:shapedefaults v:ext="edit" spidmax="1026"/><o:shapelayout v:ext="edit"><o:idmap v:ext="edit" data="1"/></o:shapelayout></w:shapeDefaults><w:docPr><w:view w:val="print"/><w:zoom w:percent="100"/><w:doNotEmbedSystemFonts/><w:proofState w:spelling="clean" w:grammar="clean"/><w:defaultTabStop w:val="720"/><w:punctuationKerning/><w:characterSpacingControl w:val="DontCompress"/><w:optimizeForBrowser/><w:relyOnVML/><w:allowPNG/><w:validateAgainstSchema/><w:saveInvalidXML w:val="off"/><w:ignoreMixedContent w:val="off"/><w:alwaysShowPlaceholderText w:val="off"/><w:compat><w:breakWrappedTables/><w:snapToGridInCell/><w:wrapTextWithPunct/><w:useAsianBreakRules/><w:dontGrowAutofit/></w:compat><wsp:rsids><wsp:rsidRoot wsp:val="004531CA"/><wsp:rsid wsp:val="000063B6"/><wsp:rsid wsp:val="00011173"/><wsp:rsid wsp:val="000223F3"/><wsp:rsid wsp:val="00053D97"/><wsp:rsid wsp:val="000603B0"/><wsp:rsid wsp:val="000706A4"/><wsp:rsid wsp:val="00080C97"/><wsp:rsid wsp:val="000A21C6"/><wsp:rsid wsp:val="000D13C6"/><wsp:rsid wsp:val="000D293F"/><wsp:rsid wsp:val="000D4A02"/><wsp:rsid wsp:val="000D66AE"/><wsp:rsid wsp:val="000E5882"/><wsp:rsid wsp:val="000F2A0B"/><wsp:rsid wsp:val="0013199F"/><wsp:rsid wsp:val="001506E2"/><wsp:rsid wsp:val="00175FF4"/><wsp:rsid wsp:val="00177666"/><wsp:rsid wsp:val="001A7337"/><wsp:rsid wsp:val="001B4168"/><wsp:rsid wsp:val="001D1704"/><wsp:rsid wsp:val="00237A3E"/><wsp:rsid wsp:val="00273831"/><wsp:rsid wsp:val="00276EF1"/><wsp:rsid wsp:val="002A5858"/><wsp:rsid wsp:val="002E03B4"/><wsp:rsid wsp:val="002F5346"/><wsp:rsid wsp:val="00306D7C"/><wsp:rsid wsp:val="00316757"/><wsp:rsid wsp:val="00330A71"/><wsp:rsid wsp:val="003E0157"/><wsp:rsid wsp:val="003E5176"/><wsp:rsid wsp:val="003F38D4"/><wsp:rsid wsp:val="00440197"/><wsp:rsid wsp:val="004531CA"/><wsp:rsid wsp:val="004726CA"/><wsp:rsid wsp:val="00480542"/><wsp:rsid wsp:val="00483C45"/><wsp:rsid wsp:val="00487441"/><wsp:rsid wsp:val="004B63EC"/><wsp:rsid wsp:val="004C5302"/><wsp:rsid wsp:val="00526473"/><wsp:rsid wsp:val="00545715"/><wsp:rsid wsp:val="00545C21"/><wsp:rsid wsp:val="005466A8"/><wsp:rsid wsp:val="00564665"/><wsp:rsid wsp:val="00575334"/><wsp:rsid wsp:val="0058519D"/><wsp:rsid wsp:val="0059525F"/><wsp:rsid wsp:val="005B05EA"/><wsp:rsid wsp:val="006052BA"/><wsp:rsid wsp:val="00634DA7"/><wsp:rsid wsp:val="006803A1"/><wsp:rsid wsp:val="006958BA"/><wsp:rsid wsp:val="00696043"/><wsp:rsid wsp:val="006B4A17"/><wsp:rsid wsp:val="006C34E0"/><wsp:rsid wsp:val="006D34BF"/><wsp:rsid wsp:val="006E6774"/><wsp:rsid wsp:val="0072153F"/><wsp:rsid wsp:val="00762861"/><wsp:rsid wsp:val="007834A3"/><wsp:rsid wsp:val="007D6ADA"/><wsp:rsid wsp:val="007F2250"/><wsp:rsid wsp:val="008022AC"/><wsp:rsid wsp:val="008200EF"/><wsp:rsid wsp:val="00820F45"/><wsp:rsid wsp:val="00881F07"/><wsp:rsid wsp:val="0089353C"/><wsp:rsid wsp:val="008E4F81"/><wsp:rsid wsp:val="008F0CE4"/><wsp:rsid wsp:val="00906B74"/><wsp:rsid wsp:val="0095527E"/><wsp:rsid wsp:val="00957A28"/><wsp:rsid wsp:val="00967690"/><wsp:rsid wsp:val="00991821"/><wsp:rsid wsp:val="00994208"/><wsp:rsid wsp:val="009A67DB"/><wsp:rsid wsp:val="009C28C2"/><wsp:rsid wsp:val="009C4DA0"/><wsp:rsid wsp:val="00A35E3F"/><wsp:rsid wsp:val="00A45629"/><wsp:rsid wsp:val="00A4714D"/><wsp:rsid wsp:val="00A674BB"/><wsp:rsid wsp:val="00A9065C"/><wsp:rsid wsp:val="00A925EE"/><wsp:rsid wsp:val="00AA5B89"/><wsp:rsid wsp:val="00AB0EB0"/><wsp:rsid wsp:val="00B12867"/><wsp:rsid wsp:val="00B138EC"/><wsp:rsid wsp:val="00B20921"/><wsp:rsid wsp:val="00B56D0E"/><wsp:rsid wsp:val="00B707F9"/><wsp:rsid wsp:val="00BC062F"/><wsp:rsid wsp:val="00BE1235"/><wsp:rsid wsp:val="00BF70E3"/><wsp:rsid wsp:val="00C03569"/><wsp:rsid wsp:val="00C1001C"/><wsp:rsid wsp:val="00C12D36"/><wsp:rsid wsp:val="00C151E8"/><wsp:rsid wsp:val="00C31A7E"/><wsp:rsid wsp:val="00C664D1"/><wsp:rsid wsp:val="00C72B37"/><wsp:rsid wsp:val="00C76F33"/><wsp:rsid wsp:val="00CC53EA"/><wsp:rsid wsp:val="00CE2F5D"/><wsp:rsid wsp:val="00CF2AA7"/><wsp:rsid wsp:val="00D03311"/><wsp:rsid wsp:val="00D2727D"/><wsp:rsid wsp:val="00D37487"/><wsp:rsid wsp:val="00D4023E"/><wsp:rsid wsp:val="00D70E88"/><wsp:rsid wsp:val="00DA6134"/><wsp:rsid wsp:val="00DB063D"/><wsp:rsid wsp:val="00DD41F9"/><wsp:rsid wsp:val="00DD7EB2"/><wsp:rsid wsp:val="00E01F4B"/><wsp:rsid wsp:val="00E551DC"/><wsp:rsid wsp:val="00E70F36"/><wsp:rsid wsp:val="00E954AC"/><wsp:rsid wsp:val="00EA2AAE"/><wsp:rsid wsp:val="00EB2D4F"/><wsp:rsid wsp:val="00EC560D"/><wsp:rsid wsp:val="00EE17F4"/><wsp:rsid wsp:val="00F1504B"/><wsp:rsid wsp:val="00F36048"/><wsp:rsid wsp:val="00F50ABD"/><wsp:rsid wsp:val="00F63D87"/><wsp:rsid wsp:val="00FB5779"/><wsp:rsid wsp:val="00FC2D6B"/><wsp:rsid wsp:val="00FF2154"/></wsp:rsids></w:docPr><w:body><wx:sect><w:tbl><w:tblPr><w:tblW w:w="14457" w:type="dxa"/><w:tblInd w:w="-1026" w:type="dxa"/></w:tblPr><w:tblGrid><w:gridCol w:w="11622"/><w:gridCol w:w="2835"/></w:tblGrid><w:tr wsp:rsidR="00A35E3F" wsp:rsidRPr="00B4325B" wsp:rsidTr="006E6774"><w:trPr><w:trHeight w:val="980"/></w:trPr><w:tc><w:tcPr><w:tcW w:w="11622" w:type="dxa"/><w:vAlign w:val="center"/></w:tcPr><w:p wsp:rsidR="00A35E3F" wsp:rsidRPr="00C20652" wsp:rsidRDefault="004B63EC" wsp:rsidP="00434EE9"><w:pPr><w:pStyle w:val="NormalWeb"/><w:spacing w:before="0" w:before-autospacing="off" w:after="0" w:after-autospacing="off" w:line="276" w:line-rule="auto"/><w:ind w:right="-18"/><w:rPr><w:b/><w:i/></w:rPr></w:pPr><w:r wsp:rsidRPr="00C20652"><w:rPr><w:b/><w:i/></w:rPr><w:fldChar w:fldCharType="begin"/></w:r><w:r wsp:rsidR="00A35E3F" wsp:rsidRPr="00C20652"><w:rPr><w:b/><w:i/></w:rPr><w:instrText> MERGEFIELD  BTEN </w:instrText></w:r><w:r wsp:rsidRPr="00C20652"><w:rPr><w:b/><w:i/></w:rPr><w:fldChar w:fldCharType="separate"/></w:r><w:r wsp:rsidR="00A35E3F" wsp:rsidRPr="00C20652"><w:rPr><w:b/><w:i/><w:noProof/></w:rPr><w:t>«BTEN»</w:t></w:r><w:r wsp:rsidRPr="00C20652"><w:rPr><w:b/><w:i/></w:rPr><w:fldChar w:fldCharType="end"/></w:r></w:p><w:p wsp:rsidR="00A35E3F" wsp:rsidRPr="004A7994" wsp:rsidRDefault="004B63EC" wsp:rsidP="00434EE9"><w:pPr><w:pStyle w:val="NormalWeb"/><w:spacing w:before="0" w:before-autospacing="off" w:after="0" w:after-autospacing="off" w:line="276" w:line-rule="auto"/><w:ind w:right="-18"/><w:rPr><w:b/><w:i/></w:rPr></w:pPr><w:r><w:rPr><w:b/><w:i/></w:rPr><w:fldChar w:fldCharType="begin"/></w:r><w:r wsp:rsidR="002F5346"><w:rPr><w:b/><w:i/></w:rPr><w:instrText> MERGEFIELD  BDIA_CHI </w:instrText></w:r><w:r><w:rPr><w:b/><w:i/></w:rPr><w:fldChar w:fldCharType="separate"/></w:r><w:r wsp:rsidR="002F5346"><w:rPr><w:b/><w:i/><w:noProof/></w:rPr><w:t>«BDIA_CHI»</w:t></w:r><w:r><w:rPr><w:b/><w:i/></w:rPr><w:fldChar w:fldCharType="end"/></w:r></w:p></w:tc><w:tc><w:tcPr><w:tcW w:w="2835" w:type="dxa"/></w:tcPr><w:p wsp:rsidR="00A35E3F" wsp:rsidRPr="00A40562" wsp:rsidRDefault="00A35E3F" wsp:rsidP="00434EE9"><w:pPr><w:pStyle w:val="NormalWeb"/><w:spacing w:before="0" w:before-autospacing="off" w:after="0" w:after-autospacing="off"/><w:ind w:right="-18"/><w:jc w:val="center"/><w:rPr><w:b/></w:rPr></w:pPr><w:r wsp:rsidRPr="00C978B5"><w:rPr><w:b/></w:rPr><w:t>PSOURCE_LOGO</w:t></w:r></w:p></w:tc></w:tr></w:tbl><w:p wsp:rsidR="00CF2AA7" wsp:rsidRDefault="00CF2AA7"/><w:p wsp:rsidR="00011173" wsp:rsidRPr="00316757" wsp:rsidRDefault="00011173" wsp:rsidP="00AA5B89"><w:pPr><w:spacing w:after="0" w:line="276" w:line-rule="auto"/><w:ind w:left="-142" w:hanging="851"/><w:jc w:val="center"/><w:rPr><w:b/><w:b-cs/><w:sz w:val="28"/><w:sz-cs w:val="28"/></w:rPr></w:pPr><w:r wsp:rsidRPr="00316757"><w:rPr><w:b/><w:b-cs/><w:sz w:val="28"/><w:sz-cs w:val="28"/></w:rPr><w:t>BẢNG KÊ ĐỀ NGHỊ THANH TOÁN BỒI THƯỜNG</w:t></w:r></w:p><w:p wsp:rsidR="00011173" wsp:rsidRPr="00526473" wsp:rsidRDefault="00011173" wsp:rsidP="00AA5B89"><w:pPr><w:pStyle w:val="NormalWeb"/><w:spacing w:before="0" w:before-autospacing="off" w:after="0" w:after-autospacing="off"/><w:ind w:right="-389" w:hanging="1134"/><w:jc w:val="center"/><w:rPr><w:b/><w:b-cs/><w:i/><w:lang w:val="FR"/></w:rPr></w:pPr><w:r wsp:rsidRPr="00526473"><w:rPr><w:b/><w:b-cs/><w:i/></w:rPr><w:t>Nghiệp vụ: </w:t></w:r><w:r wsp:rsidR="004B63EC" wsp:rsidRPr="00526473"><w:rPr><w:b/><w:b-cs/><w:i/><w:i-cs/></w:rPr><w:fldChar w:fldCharType="begin"/></w:r><w:r wsp:rsidR="00967690" wsp:rsidRPr="00526473"><w:rPr><w:b/><w:b-cs/><w:i/><w:i-cs/></w:rPr><w:instrText> MERGEFIELD  CNGHIEP_VU </w:instrText></w:r><w:r wsp:rsidR="004B63EC" wsp:rsidRPr="00526473"><w:rPr><w:b/><w:b-cs/><w:i/><w:i-cs/></w:rPr><w:fldChar w:fldCharType="separate"/></w:r><w:r wsp:rsidR="00B56D0E" wsp:rsidRPr="00526473"><w:rPr><w:b/><w:b-cs/><w:i/><w:i-cs/><w:noProof/></w:rPr><w:t>«CNGHIEP_VU»</w:t></w:r><w:r wsp:rsidR="004B63EC" wsp:rsidRPr="00526473"><w:rPr><w:b/><w:b-cs/><w:i/><w:i-cs/></w:rPr><w:fldChar w:fldCharType="end"/></w:r></w:p><w:p wsp:rsidR="00011173" wsp:rsidRPr="00526473" wsp:rsidRDefault="00011173" wsp:rsidP="00011173"><w:pPr><w:pStyle w:val="NormalWeb"/><w:spacing w:before="0" w:before-autospacing="off" w:after="0" w:after-autospacing="off"/><w:ind w:right="-389"/><w:rPr><w:b/><w:lang w:val="FR"/></w:rPr></w:pPr></w:p><w:tbl><w:tblPr><w:tblW w:w="14459" w:type="dxa"/><w:tblInd w:w="-1026" w:type="dxa"/><w:tblBorders><w:top w:val="single" w:sz="4" wx:bdrwidth="10" w:space="0" w:color="auto"/><w:left w:val="single" w:sz="4" wx:bdrwidth="10" w:space="0" w:color="auto"/><w:bottom w:val="single" w:sz="4" wx:bdrwidth="10" w:space="0" w:color="auto"/><w:right w:val="single" w:sz="4" wx:bdrwidth="10" w:space="0" w:color="auto"/><w:insideH w:val="single" w:sz="4" wx:bdrwidth="10" w:space="0" w:color="auto"/><w:insideV w:val="single" w:sz="4" wx:bdrwidth="10" w:space="0" w:color="auto"/></w:tblBorders><w:tblLook w:val="04A0"/></w:tblPr><w:tblGrid><w:gridCol w:w="893"/><w:gridCol w:w="2055"/><w:gridCol w:w="2890"/><w:gridCol w:w="1250"/><w:gridCol w:w="2827"/><w:gridCol w:w="2037"/><w:gridCol w:w="2507"/></w:tblGrid><w:tr wsp:rsidR="006C34E0" wsp:rsidTr="0089353C"><w:trPr><w:trHeight w:val="680"/></w:trPr><w:tc><w:tcPr><w:tcW w:w="893" w:type="dxa"/><w:shd w:val="clear" w:color="auto" w:fill="EDEDED"/><w:vAlign w:val="center"/></w:tcPr><w:p wsp:rsidR="00011173" wsp:rsidRPr="00526473" wsp:rsidRDefault="00011173" wsp:rsidP="002A5858"><w:pPr><w:spacing w:after="0"/><w:jc w:val="center"/><w:rPr><w:b/><w:b-cs/><w:sz w:val="24"/><w:sz-cs w:val="24"/></w:rPr></w:pPr><w:r wsp:rsidRPr="00526473"><w:rPr><w:b/><w:b-cs/><w:sz w:val="24"/><w:sz-cs w:val="24"/></w:rPr><w:t>STT</w:t></w:r></w:p></w:tc><w:tc><w:tcPr><w:tcW w:w="2055" w:type="dxa"/><w:shd w:val="clear" w:color="auto" w:fill="EDEDED"/><w:vAlign w:val="center"/></w:tcPr><w:p wsp:rsidR="00011173" wsp:rsidRPr="00526473" wsp:rsidRDefault="00011173" wsp:rsidP="002A5858"><w:pPr><w:spacing w:after="0"/><w:jc w:val="center"/><w:rPr><w:b/><w:b-cs/><w:sz w:val="24"/><w:sz-cs w:val="24"/></w:rPr></w:pPr><w:r wsp:rsidRPr="00526473"><w:rPr><w:b/><w:b-cs/><w:sz w:val="24"/><w:sz-cs w:val="24"/></w:rPr><w:t>Số hồ sơ</w:t></w:r></w:p></w:tc><w:tc><w:tcPr><w:tcW w:w="2890" w:type="dxa"/><w:shd w:val="clear" w:color="auto" w:fill="EDEDED"/><w:vAlign w:val="center"/></w:tcPr><w:p wsp:rsidR="00011173" wsp:rsidRPr="00526473" wsp:rsidRDefault="00011173" wsp:rsidP="002A5858"><w:pPr><w:spacing w:after="0"/><w:jc w:val="center"/><w:rPr><w:b/><w:b-cs/><w:sz w:val="24"/><w:sz-cs w:val="24"/></w:rPr></w:pPr><w:r wsp:rsidRPr="00526473"><w:rPr><w:b/><w:b-cs/><w:sz w:val="24"/><w:sz-cs w:val="24"/></w:rPr><w:t>Tên người thụ hưởng</w:t></w:r></w:p></w:tc><w:tc><w:tcPr><w:tcW w:w="1250" w:type="dxa"/><w:shd w:val="clear" w:color="auto" w:fill="EDEDED"/><w:vAlign w:val="center"/></w:tcPr><w:p wsp:rsidR="00011173" wsp:rsidRPr="00526473" wsp:rsidRDefault="00011173" wsp:rsidP="002A5858"><w:pPr><w:spacing w:after="0"/><w:jc w:val="center"/><w:rPr><w:b/><w:b-cs/><w:sz w:val="24"/><w:sz-cs w:val="24"/></w:rPr></w:pPr><w:r wsp:rsidRPr="00526473"><w:rPr><w:b/><w:b-cs/><w:sz w:val="24"/><w:sz-cs w:val="24"/></w:rPr><w:t>PTTT</w:t></w:r></w:p></w:tc><w:tc><w:tcPr><w:tcW w:w="2827" w:type="dxa"/><w:shd w:val="clear" w:color="auto" w:fill="EDEDED"/><w:vAlign w:val="center"/></w:tcPr><w:p wsp:rsidR="00011173" wsp:rsidRPr="00526473" wsp:rsidRDefault="00011173" wsp:rsidP="002A5858"><w:pPr><w:spacing w:after="0"/><w:jc w:val="center"/><w:rPr><w:b/><w:b-cs/><w:sz w:val="24"/><w:sz-cs w:val="24"/></w:rPr></w:pPr><w:r wsp:rsidRPr="00526473"><w:rPr><w:b/><w:b-cs/><w:sz w:val="24"/><w:sz-cs w:val="24"/></w:rPr><w:t>Số tài khoản, Ngân hàng</w:t></w:r></w:p></w:tc><w:tc><w:tcPr><w:tcW w:w="2037" w:type="dxa"/><w:shd w:val="clear" w:color="auto" w:fill="EDEDED"/><w:vAlign w:val="center"/></w:tcPr><w:p wsp:rsidR="00011173" wsp:rsidRPr="00526473" wsp:rsidRDefault="00011173" wsp:rsidP="00526473"><w:pPr><w:spacing w:after="0"/><w:jc w:val="center"/><w:rPr><w:b/><w:b-cs/><w:sz w:val="24"/><w:sz-cs w:val="24"/></w:rPr></w:pPr><w:r wsp:rsidRPr="00526473"><w:rPr><w:b/><w:b-cs/><w:sz w:val="24"/><w:sz-cs w:val="24"/></w:rPr><w:t>Số tiền </w:t></w:r></w:p></w:tc><w:tc><w:tcPr><w:tcW w:w="2507" w:type="dxa"/><w:shd w:val="clear" w:color="auto" w:fill="EDEDED"/><w:vAlign w:val="center"/></w:tcPr><w:p wsp:rsidR="00011173" wsp:rsidRPr="00526473" wsp:rsidRDefault="00011173" wsp:rsidP="002A5858"><w:pPr><w:spacing w:after="0"/><w:jc w:val="center"/><w:rPr><w:b/><w:b-cs/><w:sz w:val="24"/><w:sz-cs w:val="24"/></w:rPr></w:pPr><w:r wsp:rsidRPr="00526473"><w:rPr><w:b/><w:b-cs/><w:sz w:val="24"/><w:sz-cs w:val="24"/></w:rPr><w:t>Nội dung thanh toán</w:t></w:r></w:p></w:tc></w:tr><w:tr wsp:rsidR="006C34E0" wsp:rsidTr="0089353C"><w:trPr><w:trHeight w:val="454"/></w:trPr><w:tc><w:tcPr><w:tcW w:w="893" w:type="dxa"/><w:shd w:val="clear" w:color="auto" w:fill="auto"/><w:vAlign w:val="center"/></w:tcPr><w:p wsp:rsidR="00011173" wsp:rsidRPr="00526473" wsp:rsidRDefault="004B63EC" wsp:rsidP="00526473"><w:pPr><w:pStyle w:val="NormalWeb"/><w:spacing w:before="0" w:before-autospacing="off" w:after="0" w:after-autospacing="off"/><w:ind w:left="-102" w:right="-100"/><w:jc w:val="center"/><w:rPr><w:b-cs/><w:lang w:val="FR"/></w:rPr></w:pPr><w:r wsp:rsidRPr="00526473"><w:rPr><w:b-cs/></w:rPr><w:fldChar w:fldCharType="begin"/></w:r><w:r wsp:rsidR="00967690" wsp:rsidRPr="00526473"><w:rPr><w:b-cs/></w:rPr><w:instrText> MERGEFIELD  CSTT </w:instrText></w:r><w:r wsp:rsidRPr="00526473"><w:rPr><w:b-cs/></w:rPr><w:fldChar w:fldCharType="separate"/></w:r><w:r wsp:rsidR="00D4023E" wsp:rsidRPr="00526473"><w:rPr><w:b-cs/><w:noProof/></w:rPr><w:t>«CSTT»</w:t></w:r><w:r wsp:rsidRPr="00526473"><w:rPr><w:b-cs/></w:rPr><w:fldChar w:fldCharType="end"/></w:r></w:p></w:tc><w:tc><w:tcPr><w:tcW w:w="2055" w:type="dxa"/><w:shd w:val="clear" w:color="auto" w:fill="auto"/><w:vAlign w:val="center"/></w:tcPr><w:p wsp:rsidR="00011173" wsp:rsidRPr="00526473" wsp:rsidRDefault="004B63EC" wsp:rsidP="00526473"><w:pPr><w:pStyle w:val="NormalWeb"/><w:spacing w:before="0" w:before-autospacing="off" w:after="0" w:after-autospacing="off"/><w:ind w:right="-100"/><w:rPr><w:b-cs/><w:lang w:val="FR"/></w:rPr></w:pPr><w:r wsp:rsidRPr="00526473"><w:rPr><w:b-cs/></w:rPr><w:fldChar w:fldCharType="begin"/></w:r><w:r wsp:rsidR="00967690" wsp:rsidRPr="00526473"><w:rPr><w:b-cs/></w:rPr><w:instrText> MERGEFIELD  CSO_HS </w:instrText></w:r><w:r wsp:rsidRPr="00526473"><w:rPr><w:b-cs/></w:rPr><w:fldChar w:fldCharType="separate"/></w:r><w:r wsp:rsidR="00D4023E" wsp:rsidRPr="00526473"><w:rPr><w:b-cs/><w:noProof/></w:rPr><w:t>«CSO_HS»</w:t></w:r><w:r wsp:rsidRPr="00526473"><w:rPr><w:b-cs/></w:rPr><w:fldChar w:fldCharType="end"/></w:r></w:p></w:tc><w:tc><w:tcPr><w:tcW w:w="2890" w:type="dxa"/><w:shd w:val="clear" w:color="auto" w:fill="auto"/><w:vAlign w:val="center"/></w:tcPr><w:p wsp:rsidR="00011173" wsp:rsidRPr="00526473" wsp:rsidRDefault="004B63EC" wsp:rsidP="00526473"><w:pPr><w:pStyle w:val="NormalWeb"/><w:spacing w:before="0" w:before-autospacing="off" w:after="0" w:after-autospacing="off"/><w:ind w:right="-100"/><w:jc w:val="center"/><w:rPr><w:b-cs/><w:lang w:val="FR"/></w:rPr></w:pPr><w:r wsp:rsidRPr="00526473"><w:rPr><w:b-cs/></w:rPr><w:fldChar w:fldCharType="begin"/></w:r><w:r wsp:rsidR="00967690" wsp:rsidRPr="00526473"><w:rPr><w:b-cs/></w:rPr><w:instrText> MERGEFIELD  CNGUOI_THU_HUONG </w:instrText></w:r><w:r wsp:rsidRPr="00526473"><w:rPr><w:b-cs/></w:rPr><w:fldChar w:fldCharType="separate"/></w:r><w:r wsp:rsidR="00D4023E" wsp:rsidRPr="00526473"><w:rPr><w:b-cs/><w:noProof/></w:rPr><w:t>«CNGUOI_THU_HUONG»</w:t></w:r><w:r wsp:rsidRPr="00526473"><w:rPr><w:b-cs/></w:rPr><w:fldChar w:fldCharType="end"/></w:r></w:p></w:tc><w:tc><w:tcPr><w:tcW w:w="1250" w:type="dxa"/><w:shd w:val="clear" w:color="auto" w:fill="auto"/><w:vAlign w:val="center"/></w:tcPr><w:p wsp:rsidR="00011173" wsp:rsidRPr="00526473" wsp:rsidRDefault="004B63EC" wsp:rsidP="00545715"><w:pPr><w:pStyle w:val="NormalWeb"/><w:spacing w:before="0" w:before-autospacing="off" w:after="0" w:after-autospacing="off"/><w:ind w:right="-100"/><w:jc w:val="center"/><w:rPr><w:b-cs/><w:lang w:val="FR"/></w:rPr></w:pPr><w:r wsp:rsidRPr="00526473"><w:rPr><w:b-cs/></w:rPr><w:fldChar w:fldCharType="begin"/></w:r><w:r wsp:rsidR="00967690" wsp:rsidRPr="00526473"><w:rPr><w:b-cs/></w:rPr><w:instrText> MERGEFIELD  CPTTT </w:instrText></w:r><w:r wsp:rsidRPr="00526473"><w:rPr><w:b-cs/></w:rPr><w:fldChar w:fldCharType="separate"/></w:r><w:r wsp:rsidR="00D4023E" wsp:rsidRPr="00526473"><w:rPr><w:b-cs/><w:noProof/></w:rPr><w:t>«CPTTT»</w:t></w:r><w:r wsp:rsidRPr="00526473"><w:rPr><w:b-cs/></w:rPr><w:fldChar w:fldCharType="end"/></w:r></w:p></w:tc><w:tc><w:tcPr><w:tcW w:w="2827" w:type="dxa"/><w:shd w:val="clear" w:color="auto" w:fill="auto"/><w:vAlign w:val="center"/></w:tcPr><w:p wsp:rsidR="00011173" wsp:rsidRPr="00526473" wsp:rsidRDefault="004B63EC" wsp:rsidP="00526473"><w:pPr><w:pStyle w:val="NormalWeb"/><w:spacing w:before="0" w:before-autospacing="off" w:after="0" w:after-autospacing="off"/><w:ind w:right="-100"/><w:rPr><w:b-cs/><w:lang w:val="EN-US"/></w:rPr></w:pPr><w:r wsp:rsidRPr="00526473"><w:rPr><w:b-cs/></w:rPr><w:fldChar w:fldCharType="begin"/></w:r><w:r wsp:rsidR="001B4168" wsp:rsidRPr="00526473"><w:rPr><w:b-cs/></w:rPr><w:instrText> MERGEFIELD  CTK_CMT </w:instrText></w:r><w:r wsp:rsidRPr="00526473"><w:rPr><w:b-cs/></w:rPr><w:fldChar w:fldCharType="separate"/></w:r><w:r wsp:rsidR="00DA6134" wsp:rsidRPr="00526473"><w:rPr><w:b-cs/><w:noProof/></w:rPr><w:t>«CTK_CMT»</w:t></w:r><w:r wsp:rsidRPr="00526473"><w:rPr><w:b-cs/></w:rPr><w:fldChar w:fldCharType="end"/></w:r><w:r wsp:rsidR="001B4168" wsp:rsidRPr="00526473"><w:rPr><w:b-cs/><w:lang w:val="EN-US"/></w:rPr><w:t> - </w:t></w:r><w:r wsp:rsidRPr="00526473"><w:rPr><w:b-cs/></w:rPr><w:fldChar w:fldCharType="begin"/></w:r><w:r wsp:rsidR="001B4168" wsp:rsidRPr="00526473"><w:rPr><w:b-cs/></w:rPr><w:instrText> MERGEFIELD  CNGAN_HANG </w:instrText></w:r><w:r wsp:rsidRPr="00526473"><w:rPr><w:b-cs/></w:rPr><w:fldChar w:fldCharType="separate"/></w:r><w:r wsp:rsidR="00DA6134" wsp:rsidRPr="00526473"><w:rPr><w:b-cs/><w:noProof/></w:rPr><w:t>«CNGAN_HANG»</w:t></w:r><w:r wsp:rsidRPr="00526473"><w:rPr><w:b-cs/></w:rPr><w:fldChar w:fldCharType="end"/></w:r></w:p></w:tc><w:tc><w:tcPr><w:tcW w:w="2037" w:type="dxa"/><w:shd w:val="clear" w:color="auto" w:fill="auto"/><w:vAlign w:val="center"/></w:tcPr><w:p wsp:rsidR="00011173" wsp:rsidRPr="00526473" wsp:rsidRDefault="004B63EC" wsp:rsidP="00526473"><w:pPr><w:pStyle w:val="NormalWeb"/><w:spacing w:before="0" w:before-autospacing="off" w:after="0" w:after-autospacing="off"/><w:jc w:val="right"/><w:rPr><w:b-cs/><w:lang w:val="FR"/></w:rPr></w:pPr><w:r wsp:rsidRPr="00526473"><w:rPr><w:b-cs/></w:rPr><w:fldChar w:fldCharType="begin"/></w:r><w:r wsp:rsidR="00967690" wsp:rsidRPr="00526473"><w:rPr><w:b-cs/></w:rPr><w:instrText> MERGEFIELD  CSO_TIEN </w:instrText></w:r><w:r wsp:rsidRPr="00526473"><w:rPr><w:b-cs/></w:rPr><w:fldChar w:fldCharType="separate"/></w:r><w:r wsp:rsidR="00D4023E" wsp:rsidRPr="00526473"><w:rPr><w:b-cs/><w:noProof/></w:rPr><w:t>«CSO_TIEN»</w:t></w:r><w:r wsp:rsidRPr="00526473"><w:rPr><w:b-cs/></w:rPr><w:fldChar w:fldCharType="end"/></w:r></w:p></w:tc><w:tc><w:tcPr><w:tcW w:w="2507" w:type="dxa"/><w:shd w:val="clear" w:color="auto" w:fill="auto"/><w:vAlign w:val="center"/></w:tcPr><w:p wsp:rsidR="00011173" wsp:rsidRPr="00526473" wsp:rsidRDefault="004B63EC" wsp:rsidP="00526473"><w:pPr><w:pStyle w:val="NormalWeb"/><w:spacing w:before="0" w:before-autospacing="off" w:after="0" w:after-autospacing="off"/><w:ind w:right="-100"/><w:rPr><w:b-cs/><w:lang w:val="FR"/></w:rPr></w:pPr><w:r wsp:rsidRPr="00526473"><w:rPr><w:b-cs/></w:rPr><w:fldChar w:fldCharType="begin"/></w:r><w:r wsp:rsidR="00967690" wsp:rsidRPr="00526473"><w:rPr><w:b-cs/></w:rPr><w:instrText> MERGEFIELD  CNOI_DUNG </w:instrText></w:r><w:r wsp:rsidRPr="00526473"><w:rPr><w:b-cs/></w:rPr><w:fldChar w:fldCharType="separate"/></w:r><w:r wsp:rsidR="00D4023E" wsp:rsidRPr="00526473"><w:rPr><w:b-cs/><w:noProof/></w:rPr><w:t>«CNOI_DUNG»</w:t></w:r><w:r wsp:rsidRPr="00526473"><w:rPr><w:b-cs/></w:rPr><w:fldChar w:fldCharType="end"/></w:r></w:p></w:tc><aml:annotation aml:id="0" w:type="Word.Bookmark.Start" w:name="CWMLRepeat"/><aml:annotation aml:id="0" w:type="Word.Bookmark.End"/></w:tr><w:tr wsp:rsidR="00316757" wsp:rsidTr="0089353C"><w:trPr><w:trHeight w:val="454"/></w:trPr><w:tc><w:tcPr><w:tcW w:w="9915" w:type="dxa"/><w:gridSpan w:val="5"/><w:shd w:val="clear" w:color="auto" w:fill="auto"/><w:vAlign w:val="center"/></w:tcPr><w:p wsp:rsidR="00316757" wsp:rsidRPr="00440197" wsp:rsidRDefault="00316757" wsp:rsidP="00BC062F"><w:pPr><w:pStyle w:val="NormalWeb"/><w:spacing w:before="0" w:before-autospacing="off" w:after="0" w:after-autospacing="off"/><w:ind w:right="-100"/><w:jc w:val="center"/><w:rPr><w:b/><w:lang w:val="EN-US"/></w:rPr></w:pPr><w:r wsp:rsidRPr="00526473"><w:rPr><w:b/></w:rPr><w:t>Tổng cộng</w:t></w:r><w:r wsp:rsidR="00440197"><w:rPr><w:b/><w:lang w:val="EN-US"/></w:rPr><w:t> (VN</w:t></w:r><w:r wsp:rsidR="00BC062F"><w:rPr><w:b/><w:lang w:val="EN-US"/></w:rPr><w:t>Đ</w:t></w:r><w:r wsp:rsidR="00440197"><w:rPr><w:b/><w:lang w:val="EN-US"/></w:rPr><w:t>)</w:t></w:r></w:p></w:tc><w:tc><w:tcPr><w:tcW w:w="2037" w:type="dxa"/><w:shd w:val="clear" w:color="auto" w:fill="auto"/><w:vAlign w:val="center"/></w:tcPr><w:p wsp:rsidR="00316757" wsp:rsidRPr="000063B6" wsp:rsidRDefault="004B63EC" wsp:rsidP="00526473"><w:pPr><w:pStyle w:val="NormalWeb"/><w:spacing w:before="0" w:before-autospacing="off" w:after="0" w:after-autospacing="off"/><w:jc w:val="right"/><w:rPr><w:b/><w:b-cs/></w:rPr></w:pPr><w:r wsp:rsidRPr="000063B6"><w:rPr><w:b/></w:rPr><w:fldChar w:fldCharType="begin"/></w:r><w:r wsp:rsidR="00316757" wsp:rsidRPr="000063B6"><w:rPr><w:b/></w:rPr><w:instrText> MERGEFIELD  BTONG_TIEN </w:instrText></w:r><w:r wsp:rsidRPr="000063B6"><w:rPr><w:b/></w:rPr><w:fldChar w:fldCharType="separate"/></w:r><w:r wsp:rsidR="00316757" wsp:rsidRPr="000063B6"><w:rPr><w:b/><w:noProof/></w:rPr><w:t>«BTONG_TIEN»</w:t></w:r><w:r wsp:rsidRPr="000063B6"><w:rPr><w:b/></w:rPr><w:fldChar w:fldCharType="end"/></w:r></w:p></w:tc><w:tc><w:tcPr><w:tcW w:w="2507" w:type="dxa"/><w:shd w:val="clear" w:color="auto" w:fill="auto"/><w:vAlign w:val="center"/></w:tcPr><w:p wsp:rsidR="00316757" wsp:rsidRPr="00526473" wsp:rsidRDefault="00316757" wsp:rsidP="00526473"><w:pPr><w:pStyle w:val="NormalWeb"/><w:spacing w:before="0" w:before-autospacing="off" w:after="0" w:after-autospacing="off"/><w:ind w:right="-389"/><w:jc w:val="center"/><w:rPr><w:b-cs/></w:rPr></w:pPr></w:p></w:tc></w:tr></w:tbl><w:p wsp:rsidR="00011173" wsp:rsidRDefault="00011173" wsp:rsidP="00011173"/><w:tbl><w:tblPr><w:tblW w:w="0" w:type="auto"/><w:tblInd w:w="-1026" w:type="dxa"/><w:tblLook w:val="04A0"/></w:tblPr><w:tblGrid><w:gridCol w:w="6229"/><w:gridCol w:w="8230"/></w:tblGrid><w:tr wsp:rsidR="00011173" wsp:rsidTr="00AA5B89"><w:trPr><w:trHeight w:val="454"/></w:trPr><w:tc><w:tcPr><w:tcW w:w="6229" w:type="dxa"/><w:shd w:val="clear" w:color="auto" w:fill="auto"/><w:vAlign w:val="center"/></w:tcPr><w:p wsp:rsidR="00011173" wsp:rsidRDefault="00011173" wsp:rsidP="00526473"><w:pPr><w:spacing w:after="0" w:line="276" w:line-rule="auto"/><w:jc w:val="center"/></w:pPr></w:p></w:tc><w:tc><w:tcPr><w:tcW w:w="8230" w:type="dxa"/><w:shd w:val="clear" w:color="auto" w:fill="auto"/><w:vAlign w:val="center"/></w:tcPr><w:p wsp:rsidR="00011173" wsp:rsidRPr="00526473" wsp:rsidRDefault="00A9065C" wsp:rsidP="00526473"><w:pPr><w:spacing w:after="0" w:line="276" w:line-rule="auto"/><w:jc w:val="center"/><w:rPr><w:i/><w:sz w:val="24"/><w:sz-cs w:val="24"/></w:rPr></w:pPr><w:r wsp:rsidRPr="00526473"><w:rPr><w:b-cs/><w:i/><w:snapToGrid w:val="off"/><w:sz w:val="24"/><w:sz-cs w:val="24"/></w:rPr><w:t>Ngày </w:t></w:r><w:r wsp:rsidR="004B63EC" wsp:rsidRPr="00526473"><w:rPr><w:i/><w:sz w:val="24"/><w:sz-cs w:val="24"/></w:rPr><w:fldChar w:fldCharType="begin"/></w:r><w:r wsp:rsidRPr="00526473"><w:rPr><w:i/><w:sz w:val="24"/><w:sz-cs w:val="24"/></w:rPr><w:instrText> MERGEFIELD  BNGAY </w:instrText></w:r><w:r wsp:rsidR="004B63EC" wsp:rsidRPr="00526473"><w:rPr><w:i/><w:sz w:val="24"/><w:sz-cs w:val="24"/></w:rPr><w:fldChar w:fldCharType="separate"/></w:r><w:r wsp:rsidRPr="00526473"><w:rPr><w:i/><w:noProof/><w:sz w:val="24"/><w:sz-cs w:val="24"/></w:rPr><w:t>«BNGAY»</w:t></w:r><w:r wsp:rsidR="004B63EC" wsp:rsidRPr="00526473"><w:rPr><w:i/><w:sz w:val="24"/><w:sz-cs w:val="24"/></w:rPr><w:fldChar w:fldCharType="end"/></w:r><w:r wsp:rsidRPr="00526473"><w:rPr><w:b/><w:i/><w:sz w:val="24"/><w:sz-cs w:val="24"/></w:rPr><w:t> </w:t></w:r><w:r wsp:rsidRPr="00526473"><w:rPr><w:i/><w:sz w:val="24"/><w:sz-cs w:val="24"/></w:rPr><w:t>tháng </w:t></w:r><w:r wsp:rsidR="004B63EC" wsp:rsidRPr="00526473"><w:rPr><w:i/><w:sz w:val="24"/><w:sz-cs w:val="24"/></w:rPr><w:fldChar w:fldCharType="begin"/></w:r><w:r wsp:rsidRPr="00526473"><w:rPr><w:i/><w:sz w:val="24"/><w:sz-cs w:val="24"/></w:rPr><w:instrText> MERGEFIELD  BTHANG </w:instrText></w:r><w:r wsp:rsidR="004B63EC" wsp:rsidRPr="00526473"><w:rPr><w:i/><w:sz w:val="24"/><w:sz-cs w:val="24"/></w:rPr><w:fldChar w:fldCharType="separate"/></w:r><w:r wsp:rsidRPr="00526473"><w:rPr><w:i/><w:noProof/><w:sz w:val="24"/><w:sz-cs w:val="24"/></w:rPr><w:t>«BTHANG»</w:t></w:r><w:r wsp:rsidR="004B63EC" wsp:rsidRPr="00526473"><w:rPr><w:i/><w:sz w:val="24"/><w:sz-cs w:val="24"/></w:rPr><w:fldChar w:fldCharType="end"/></w:r><w:r wsp:rsidRPr="00526473"><w:rPr><w:b/><w:i/><w:sz w:val="24"/><w:sz-cs w:val="24"/></w:rPr><w:t> </w:t></w:r><w:r wsp:rsidRPr="00526473"><w:rPr><w:i/><w:sz w:val="24"/><w:sz-cs w:val="24"/></w:rPr><w:t>năm </w:t></w:r><w:r wsp:rsidR="004B63EC" wsp:rsidRPr="00526473"><w:rPr><w:i/><w:sz w:val="24"/><w:sz-cs w:val="24"/></w:rPr><w:fldChar w:fldCharType="begin"/></w:r><w:r wsp:rsidRPr="00526473"><w:rPr><w:i/><w:sz w:val="24"/><w:sz-cs w:val="24"/></w:rPr><w:instrText> MERGEFIELD  BNAM </w:instrText></w:r><w:r wsp:rsidR="004B63EC" wsp:rsidRPr="00526473"><w:rPr><w:i/><w:sz w:val="24"/><w:sz-cs w:val="24"/></w:rPr><w:fldChar w:fldCharType="separate"/></w:r><w:r wsp:rsidRPr="00526473"><w:rPr><w:i/><w:noProof/><w:sz w:val="24"/><w:sz-cs w:val="24"/></w:rPr><w:t>«BNAM»</w:t></w:r><w:r wsp:rsidR="004B63EC" wsp:rsidRPr="00526473"><w:rPr><w:i/><w:sz w:val="24"/><w:sz-cs w:val="24"/></w:rPr><w:fldChar w:fldCharType="end"/></w:r></w:p></w:tc></w:tr><w:tr wsp:rsidR="00011173" wsp:rsidTr="00AA5B89"><w:tc><w:tcPr><w:tcW w:w="6229" w:type="dxa"/><w:shd w:val="clear" w:color="auto" w:fill="auto"/><w:vAlign w:val="center"/></w:tcPr><w:p wsp:rsidR="00011173" wsp:rsidRPr="00526473" wsp:rsidRDefault="00011173" wsp:rsidP="00526473"><w:pPr><w:spacing w:after="0" w:line="276" w:line-rule="auto"/><w:jc w:val="center"/><w:rPr><w:b/><w:b-cs/><w:sz w:val="24"/><w:sz-cs w:val="24"/></w:rPr></w:pPr><w:r wsp:rsidRPr="00526473"><w:rPr><w:b/><w:b-cs/><w:sz w:val="24"/><w:sz-cs w:val="24"/></w:rPr><w:t>LÃNH ĐẠO ĐƠN VỊ</w:t></w:r></w:p><w:p wsp:rsidR="00526473" wsp:rsidRPr="00526473" wsp:rsidRDefault="00526473" wsp:rsidP="00526473"><w:pPr><w:spacing w:after="0" w:line="276" w:line-rule="auto"/><w:jc w:val="center"/><w:rPr><w:i/><w:i-cs/><w:sz w:val="24"/><w:sz-cs w:val="24"/><w:lang w:val="EN-US"/></w:rPr></w:pPr><w:r wsp:rsidRPr="00526473"><w:rPr><w:i/><w:i-cs/><w:sz w:val="24"/><w:sz-cs w:val="24"/><w:lang w:val="EN-US"/></w:rPr><w:t>(</w:t></w:r><w:proofErr w:type="spellStart"/><w:r wsp:rsidRPr="00526473"><w:rPr><w:i/><w:i-cs/><w:sz w:val="24"/><w:sz-cs w:val="24"/><w:lang w:val="EN-US"/></w:rPr><w:t>Kí</w:t></w:r><w:proofErr w:type="spellEnd"/><w:r wsp:rsidRPr="00526473"><w:rPr><w:i/><w:i-cs/><w:sz w:val="24"/><w:sz-cs w:val="24"/><w:lang w:val="EN-US"/></w:rPr><w:t>, </w:t></w:r><w:proofErr w:type="spellStart"/><w:r wsp:rsidRPr="00526473"><w:rPr><w:i/><w:i-cs/><w:sz w:val="24"/><w:sz-cs w:val="24"/><w:lang w:val="EN-US"/></w:rPr><w:t>ghi</w:t></w:r><w:proofErr w:type="spellEnd"/><w:r wsp:rsidRPr="00526473"><w:rPr><w:i/><w:i-cs/><w:sz w:val="24"/><w:sz-cs w:val="24"/><w:lang w:val="EN-US"/></w:rPr><w:t> </w:t></w:r><w:proofErr w:type="spellStart"/><w:r wsp:rsidRPr="00526473"><w:rPr><w:i/><w:i-cs/><w:sz w:val="24"/><w:sz-cs w:val="24"/><w:lang w:val="EN-US"/></w:rPr><w:t>rõ</w:t></w:r><w:proofErr w:type="spellEnd"/><w:r wsp:rsidRPr="00526473"><w:rPr><w:i/><w:i-cs/><w:sz w:val="24"/><w:sz-cs w:val="24"/><w:lang w:val="EN-US"/></w:rPr><w:t> </w:t></w:r><w:proofErr w:type="spellStart"/><w:r wsp:rsidRPr="00526473"><w:rPr><w:i/><w:i-cs/><w:sz w:val="24"/><w:sz-cs w:val="24"/><w:lang w:val="EN-US"/></w:rPr><w:t>họ</w:t></w:r><w:proofErr w:type="spellEnd"/><w:r wsp:rsidRPr="00526473"><w:rPr><w:i/><w:i-cs/><w:sz w:val="24"/><w:sz-cs w:val="24"/><w:lang w:val="EN-US"/></w:rPr><w:t> </w:t></w:r><w:proofErr w:type="spellStart"/><w:r wsp:rsidRPr="00526473"><w:rPr><w:i/><w:i-cs/><w:sz w:val="24"/><w:sz-cs w:val="24"/><w:lang w:val="EN-US"/></w:rPr><w:t>tên</w:t></w:r><w:proofErr w:type="spellEnd"/><w:r wsp:rsidRPr="00526473"><w:rPr><w:i/><w:i-cs/><w:sz w:val="24"/><w:sz-cs w:val="24"/><w:lang w:val="EN-US"/></w:rPr><w:t>)</w:t></w:r></w:p></w:tc><w:tc><w:tcPr><w:tcW w:w="8230" w:type="dxa"/><w:shd w:val="clear" w:color="auto" w:fill="auto"/><w:vAlign w:val="center"/></w:tcPr><w:p wsp:rsidR="00011173" wsp:rsidRPr="00526473" wsp:rsidRDefault="00011173" wsp:rsidP="00526473"><w:pPr><w:spacing w:after="0" w:line="276" w:line-rule="auto"/><w:jc w:val="center"/><w:rPr><w:b/><w:b-cs/><w:sz w:val="24"/><w:sz-cs w:val="24"/></w:rPr></w:pPr><w:r wsp:rsidRPr="00526473"><w:rPr><w:b/><w:b-cs/><w:sz w:val="24"/><w:sz-cs w:val="24"/></w:rPr><w:t>NGƯỜI LẬP BẢNG KÊ</w:t></w:r></w:p><w:p wsp:rsidR="00526473" wsp:rsidRPr="00526473" wsp:rsidRDefault="00526473" wsp:rsidP="00526473"><w:pPr><w:spacing w:after="0" w:line="276" w:line-rule="auto"/><w:jc w:val="center"/><w:rPr><w:i/><w:i-cs/><w:sz w:val="24"/><w:sz-cs w:val="24"/><w:lang w:val="EN-US"/></w:rPr></w:pPr><w:r wsp:rsidRPr="00526473"><w:rPr><w:i/><w:i-cs/><w:sz w:val="24"/><w:sz-cs w:val="24"/><w:lang w:val="EN-US"/></w:rPr><w:t>(</w:t></w:r><w:proofErr w:type="spellStart"/><w:r wsp:rsidRPr="00526473"><w:rPr><w:i/><w:i-cs/><w:sz w:val="24"/><w:sz-cs w:val="24"/><w:lang w:val="EN-US"/></w:rPr><w:t>Kí</w:t></w:r><w:proofErr w:type="spellEnd"/><w:r wsp:rsidRPr="00526473"><w:rPr><w:i/><w:i-cs/><w:sz w:val="24"/><w:sz-cs w:val="24"/><w:lang w:val="EN-US"/></w:rPr><w:t>, </w:t></w:r><w:proofErr w:type="spellStart"/><w:r wsp:rsidRPr="00526473"><w:rPr><w:i/><w:i-cs/><w:sz w:val="24"/><w:sz-cs w:val="24"/><w:lang w:val="EN-US"/></w:rPr><w:t>ghi</w:t></w:r><w:proofErr w:type="spellEnd"/><w:r wsp:rsidRPr="00526473"><w:rPr><w:i/><w:i-cs/><w:sz w:val="24"/><w:sz-cs w:val="24"/><w:lang w:val="EN-US"/></w:rPr><w:t> </w:t></w:r><w:proofErr w:type="spellStart"/><w:r wsp:rsidRPr="00526473"><w:rPr><w:i/><w:i-cs/><w:sz w:val="24"/><w:sz-cs w:val="24"/><w:lang w:val="EN-US"/></w:rPr><w:t>rõ</w:t></w:r><w:proofErr w:type="spellEnd"/><w:r wsp:rsidRPr="00526473"><w:rPr><w:i/><w:i-cs/><w:sz w:val="24"/><w:sz-cs w:val="24"/><w:lang w:val="EN-US"/></w:rPr><w:t> </w:t></w:r><w:proofErr w:type="spellStart"/><w:r wsp:rsidRPr="00526473"><w:rPr><w:i/><w:i-cs/><w:sz w:val="24"/><w:sz-cs w:val="24"/><w:lang w:val="EN-US"/></w:rPr><w:t>họ</w:t></w:r><w:proofErr w:type="spellEnd"/><w:r wsp:rsidRPr="00526473"><w:rPr><w:i/><w:i-cs/><w:sz w:val="24"/><w:sz-cs w:val="24"/><w:lang w:val="EN-US"/></w:rPr><w:t> </w:t></w:r><w:proofErr w:type="spellStart"/><w:r wsp:rsidRPr="00526473"><w:rPr><w:i/><w:i-cs/><w:sz w:val="24"/><w:sz-cs w:val="24"/><w:lang w:val="EN-US"/></w:rPr><w:t>tên</w:t></w:r><w:proofErr w:type="spellEnd"/><w:r wsp:rsidRPr="00526473"><w:rPr><w:i/><w:i-cs/><w:sz w:val="24"/><w:sz-cs w:val="24"/><w:lang w:val="EN-US"/></w:rPr><w:t>)</w:t></w:r></w:p></w:tc></w:tr></w:tbl><w:p wsp:rsidR="00011173" wsp:rsidRDefault="00011173" wsp:rsidP="00011173"/><w:sectPr wsp:rsidR="00011173" wsp:rsidSect="00306D7C"><w:pgSz w:w="15842" w:h="12242" w:code="1"/><w:pgMar w:top="851" w:right="674" w:bottom="1440" w:left="1803" w:header="720" w:footer="720" w:gutter="0"/><w:cols w:space="720"/><w:docGrid w:line-pitch="360"/></w:sectPr></wx:sect></w:body></w:wordDocument>