<?xml version="1.0" encoding="UTF-8" standalone="yes"?>
<?mso-application progid="Word.Document"?>
<w:wordDocument xmlns:aml="http://schemas.microsoft.com/aml/2001/core" xmlns:wpc="http://schemas.microsoft.com/office/word/2010/wordprocessingCanvas" xmlns:cx="http://schemas.microsoft.com/office/drawing/2014/chartex" xmlns:cx1="http://schemas.microsoft.com/office/drawing/2015/9/8/chartex" xmlns:dt="uuid:C2F41010-65B3-11d1-A29F-00AA00C14882" xmlns:mc="http://schemas.openxmlformats.org/markup-compatibility/2006" xmlns:o="urn:schemas-microsoft-com:office:office" xmlns:v="urn:schemas-microsoft-com:vml" xmlns:w10="urn:schemas-microsoft-com:office:word" xmlns:w="http://schemas.microsoft.com/office/word/2003/wordml" xmlns:wx="http://schemas.microsoft.com/office/word/2003/auxHint" xmlns:wne="http://schemas.microsoft.com/office/word/2006/wordml" xmlns:wsp="http://schemas.microsoft.com/office/word/2003/wordml/sp2" xmlns:sl="http://schemas.microsoft.com/schemaLibrary/2003/core" xmlns:ns0="http://schemas.microsoft.com/office/drawing/2015/10/21/chartex" xmlns:ns1="http://schemas.microsoft.com/office/drawing/2016/5/9/chartex" xmlns:ns2="http://schemas.microsoft.com/office/drawing/2016/5/10/chartex" xmlns:ns3="http://schemas.microsoft.com/office/drawing/2016/5/11/chartex" xmlns:ns4="http://schemas.microsoft.com/office/drawing/2016/5/12/chartex" xmlns:ns5="http://schemas.microsoft.com/office/drawing/2016/5/13/chartex" xmlns:ns6="http://schemas.microsoft.com/office/drawing/2016/5/14/chartex" xmlns:ns7="http://schemas.microsoft.com/office/drawing/2016/ink" xmlns:ns8="http://schemas.microsoft.com/office/drawing/2017/model3d" w:macrosPresent="no" w:embeddedObjPresent="no" w:ocxPresent="no" xml:space="preserve"><w:ignoreSubtree w:val="http://schemas.microsoft.com/office/word/2003/wordml/sp2"/><o:DocumentProperties><o:Author>HUNGLE.VBI</o:Author><o:LastAuthor>Nguyen Tien Nam</o:LastAuthor><o:Revision>52</o:Revision><o:TotalTime>45</o:TotalTime><o:LastPrinted>2015-04-03T06:34:00Z</o:LastPrinted><o:Created>2020-12-02T03:14:00Z</o:Created><o:LastSaved>2021-11-01T08:09:00Z</o:LastSaved><o:Pages>1</o:Pages><o:Words>143</o:Words><o:Characters>820</o:Characters><o:Company>2-8-2010</o:Company><o:Lines>6</o:Lines><o:Paragraphs>1</o:Paragraphs><o:CharactersWithSpaces>962</o:CharactersWithSpaces><o:Version>16</o:Version></o:DocumentProperties><w:fonts><w:defaultFonts w:ascii="Calibri" w:fareast="Calibri" w:h-ansi="Calibri" w:cs="Times New Roman"/><w:font w:name="Times New Roman"><w:panose-1 w:val="02020603050405020304"/><w:charset w:val="00"/><w:family w:val="Roman"/><w:pitch w:val="variable"/><w:sig w:usb-0="E0002EFF" w:usb-1="C000785B" w:usb-2="00000009" w:usb-3="00000000" w:csb-0="000001FF" w:csb-1="00000000"/></w:font><w:font w:name="Courier New"><w:panose-1 w:val="02070309020205020404"/><w:charset w:val="00"/><w:family w:val="Modern"/><w:pitch w:val="fixed"/><w:sig w:usb-0="E0002EFF" w:usb-1="C0007843" w:usb-2="00000009" w:usb-3="00000000" w:csb-0="000001FF" w:csb-1="00000000"/></w:font><w:font w:name="Symbol"><w:panose-1 w:val="05050102010706020507"/><w:charset w:val="02"/><w:family w:val="Roman"/><w:pitch w:val="variable"/><w:sig w:usb-0="00000000" w:usb-1="10000000" w:usb-2="00000000" w:usb-3="00000000" w:csb-0="80000000" w:csb-1="00000000"/></w:font><w:font w:name="Wingdings"><w:panose-1 w:val="05000000000000000000"/><w:charset w:val="02"/><w:family w:val="auto"/><w:pitch w:val="variable"/><w:sig w:usb-0="00000000" w:usb-1="10000000" w:usb-2="00000000" w:usb-3="00000000" w:csb-0="80000000" w:csb-1="00000000"/></w:font><w:font w:name="Wingdings"><w:panose-1 w:val="05000000000000000000"/><w:charset w:val="02"/><w:family w:val="auto"/><w:pitch w:val="variable"/><w:sig w:usb-0="00000000" w:usb-1="10000000" w:usb-2="00000000" w:usb-3="00000000" w:csb-0="80000000" w:csb-1="00000000"/></w:font><w:font w:name="Calibri"><w:panose-1 w:val="020F0502020204030204"/><w:charset w:val="00"/><w:family w:val="Swiss"/><w:pitch w:val="variable"/><w:sig w:usb-0="E4002EFF" w:usb-1="C000247B" w:usb-2="00000009" w:usb-3="00000000" w:csb-0="000001FF" w:csb-1="00000000"/></w:font><w:font w:name="Tahoma"><w:panose-1 w:val="020B0604030504040204"/><w:charset w:val="00"/><w:family w:val="Swiss"/><w:pitch w:val="variable"/><w:sig w:usb-0="E1002EFF" w:usb-1="C000605B" w:usb-2="00000029" w:usb-3="00000000" w:csb-0="000101FF" w:csb-1="00000000"/></w:font></w:fonts><w:lists><w:listDef w:listDefId="0"><w:lsid w:val="36F04C8E"/><w:plt w:val="HybridMultilevel"/><w:tmpl w:val="211A45BA"/><w:lvl w:ilvl="0" w:tplc="A8A2EE78"><w:nfc w:val="23"/><w:lvlText w:val="-"/><w:lvlJc w:val="left"/><w:pPr><w:ind w:left="720" w:hanging="360"/></w:pPr><w:rPr><w:rFonts w:ascii="Times New Roman" w:fareast="Times New Roman" w:h-ansi="Times New Roman" w:cs="Times New Roman" w:hint="default"/></w:rPr></w:lvl><w:lvl w:ilvl="1" w:tplc="04090003" w:tentative="on"><w:start w:val="1"/><w:nfc w:val="23"/><w:lvlText w:val="o"/><w:lvlJc w:val="left"/><w:pPr><w:ind w:left="1440" w:hanging="360"/></w:pPr><w:rPr><w:rFonts w:ascii="Courier New" w:h-ansi="Courier New" w:cs="Courier New" w:hint="default"/></w:rPr></w:lvl><w:lvl w:ilvl="2" w:tplc="04090005" w:tentative="on"><w:start w:val="1"/><w:nfc w:val="23"/><w:lvlText w:val=""/><w:lvlJc w:val="left"/><w:pPr><w:ind w:left="2160" w:hanging="360"/></w:pPr><w:rPr><w:rFonts w:ascii="Wingdings" w:h-ansi="Wingdings" w:hint="default"/></w:rPr></w:lvl><w:lvl w:ilvl="3" w:tplc="04090001" w:tentative="on"><w:start w:val="1"/><w:nfc w:val="23"/><w:lvlText w:val=""/><w:lvlJc w:val="left"/><w:pPr><w:ind w:left="2880" w:hanging="360"/></w:pPr><w:rPr><w:rFonts w:ascii="Symbol" w:h-ansi="Symbol" w:hint="default"/></w:rPr></w:lvl><w:lvl w:ilvl="4" w:tplc="04090003" w:tentative="on"><w:start w:val="1"/><w:nfc w:val="23"/><w:lvlText w:val="o"/><w:lvlJc w:val="left"/><w:pPr><w:ind w:left="3600" w:hanging="360"/></w:pPr><w:rPr><w:rFonts w:ascii="Courier New" w:h-ansi="Courier New" w:cs="Courier New" w:hint="default"/></w:rPr></w:lvl><w:lvl w:ilvl="5" w:tplc="04090005" w:tentative="on"><w:start w:val="1"/><w:nfc w:val="23"/><w:lvlText w:val=""/><w:lvlJc w:val="left"/><w:pPr><w:ind w:left="4320" w:hanging="360"/></w:pPr><w:rPr><w:rFonts w:ascii="Wingdings" w:h-ansi="Wingdings" w:hint="default"/></w:rPr></w:lvl><w:lvl w:ilvl="6" w:tplc="04090001" w:tentative="on"><w:start w:val="1"/><w:nfc w:val="23"/><w:lvlText w:val=""/><w:lvlJc w:val="left"/><w:pPr><w:ind w:left="5040" w:hanging="360"/></w:pPr><w:rPr><w:rFonts w:ascii="Symbol" w:h-ansi="Symbol" w:hint="default"/></w:rPr></w:lvl><w:lvl w:ilvl="7" w:tplc="04090003" w:tentative="on"><w:start w:val="1"/><w:nfc w:val="23"/><w:lvlText w:val="o"/><w:lvlJc w:val="left"/><w:pPr><w:ind w:left="5760" w:hanging="360"/></w:pPr><w:rPr><w:rFonts w:ascii="Courier New" w:h-ansi="Courier New" w:cs="Courier New" w:hint="default"/></w:rPr></w:lvl><w:lvl w:ilvl="8" w:tplc="04090005" w:tentative="on"><w:start w:val="1"/><w:nfc w:val="23"/><w:lvlText w:val=""/><w:lvlJc w:val="left"/><w:pPr><w:ind w:left="6480" w:hanging="360"/></w:pPr><w:rPr><w:rFonts w:ascii="Wingdings" w:h-ansi="Wingdings" w:hint="default"/></w:rPr></w:lvl></w:listDef><w:list w:ilfo="1"><w:ilst w:val="0"/></w:list></w:lists><w:styles><w:versionOfBuiltInStylenames w:val="7"/><w:latentStyles w:defLockedState="off" w:latentStyleCount="371"><w:lsdException w:name="Normal"/><w:lsdException w:name="heading 1"/><w:lsdException w:name="heading 2"/><w:lsdException w:name="heading 3"/><w:lsdException w:name="heading 4"/><w:lsdException w:name="heading 5"/><w:lsdException w:name="heading 6"/><w:lsdException w:name="heading 7"/><w:lsdException w:name="heading 8"/><w:lsdException w:name="heading 9"/><w:lsdException w:name="caption"/><w:lsdException w:name="Title"/><w:lsdException w:name="Subtitle"/><w:lsdException w:name="Strong"/><w:lsdException w:name="Emphasis"/><w:lsdException w:name="Normal Table"/><w:lsdException w:name="Table Simple 1"/><w:lsdException w:name="Table Simple 2"/><w:lsdException w:name="Table Simple 3"/><w:lsdException w:name="Table Classic 1"/><w:lsdException w:name="Table Classic 2"/><w:lsdException w:name="Table Classic 3"/><w:lsdException w:name="Table Classic 4"/><w:lsdException w:name="Table Colorful 1"/><w:lsdException w:name="Table Colorful 2"/><w:lsdException w:name="Table Colorful 3"/><w:lsdException w:name="Table Columns 1"/><w:lsdException w:name="Table Columns 2"/><w:lsdException w:name="Table Columns 3"/><w:lsdException w:name="Table Columns 4"/><w:lsdException w:name="Table Columns 5"/><w:lsdException w:name="Table Grid 1"/><w:lsdException w:name="Table Grid 2"/><w:lsdException w:name="Table Grid 3"/><w:lsdException w:name="Table Grid 4"/><w:lsdException w:name="Table Grid 5"/><w:lsdException w:name="Table Grid 6"/><w:lsdException w:name="Table Grid 7"/><w:lsdException w:name="Table Grid 8"/><w:lsdException w:name="Table List 1"/><w:lsdException w:name="Table List 2"/><w:lsdException w:name="Table List 3"/><w:lsdException w:name="Table List 4"/><w:lsdException w:name="Table List 5"/><w:lsdException w:name="Table List 6"/><w:lsdException w:name="Table List 7"/><w:lsdException w:name="Table List 8"/><w:lsdException w:name="Table 3D effects 1"/><w:lsdException w:name="Table 3D effects 2"/><w:lsdException w:name="Table 3D effects 3"/><w:lsdException w:name="Table Contemporary"/><w:lsdException w:name="Table Elegant"/><w:lsdException w:name="Table Professional"/><w:lsdException w:name="Table Subtle 1"/><w:lsdException w:name="Table Subtle 2"/><w:lsdException w:name="Table Web 1"/><w:lsdException w:name="Table Web 2"/><w:lsdException w:name="Table Web 3"/><w:lsdException w:name="Table Theme"/><w:lsdException w:name="No Spacing"/><w:lsdException w:name="Light Shading"/><w:lsdException w:name="Light List"/><w:lsdException w:name="Light Grid"/><w:lsdException w:name="Medium Shading 1"/><w:lsdException w:name="Medium Shading 2"/><w:lsdException w:name="Medium List 1"/><w:lsdException w:name="Medium List 2"/><w:lsdException w:name="Medium Grid 1"/><w:lsdException w:name="Medium Grid 2"/><w:lsdException w:name="Medium Grid 3"/><w:lsdException w:name="Dark List"/><w:lsdException w:name="Colorful Shading"/><w:lsdException w:name="Colorful List"/><w:lsdException w:name="Colorful Grid"/><w:lsdException w:name="Light Shading Accent 1"/><w:lsdException w:name="Light List Accent 1"/><w:lsdException w:name="Light Grid Accent 1"/><w:lsdException w:name="Medium Shading 1 Accent 1"/><w:lsdException w:name="Medium Shading 2 Accent 1"/><w:lsdException w:name="Medium List 1 Accent 1"/><w:lsdException w:name="List Paragraph"/><w:lsdException w:name="Quote"/><w:lsdException w:name="Intense Quote"/><w:lsdException w:name="Medium List 2 Accent 1"/><w:lsdException w:name="Medium Grid 1 Accent 1"/><w:lsdException w:name="Medium Grid 2 Accent 1"/><w:lsdException w:name="Medium Grid 3 Accent 1"/><w:lsdException w:name="Dark List Accent 1"/><w:lsdException w:name="Colorful Shading Accent 1"/><w:lsdException w:name="Colorful List Accent 1"/><w:lsdException w:name="Colorful Grid Accent 1"/><w:lsdException w:name="Light Shading Accent 2"/><w:lsdException w:name="Light List Accent 2"/><w:lsdException w:name="Light Grid Accent 2"/><w:lsdException w:name="Medium Shading 1 Accent 2"/><w:lsdException w:name="Medium Shading 2 Accent 2"/><w:lsdException w:name="Medium List 1 Accent 2"/><w:lsdException w:name="Medium List 2 Accent 2"/><w:lsdException w:name="Medium Grid 1 Accent 2"/><w:lsdException w:name="Medium Grid 2 Accent 2"/><w:lsdException w:name="Medium Grid 3 Accent 2"/><w:lsdException w:name="Dark List Accent 2"/><w:lsdException w:name="Colorful Shading Accent 2"/><w:lsdException w:name="Colorful List Accent 2"/><w:lsdException w:name="Colorful Grid Accent 2"/><w:lsdException w:name="Light Shading Accent 3"/><w:lsdException w:name="Light List Accent 3"/><w:lsdException w:name="Light Grid Accent 3"/><w:lsdException w:name="Medium Shading 1 Accent 3"/><w:lsdException w:name="Medium Shading 2 Accent 3"/><w:lsdException w:name="Medium List 1 Accent 3"/><w:lsdException w:name="Medium List 2 Accent 3"/><w:lsdException w:name="Medium Grid 1 Accent 3"/><w:lsdException w:name="Medium Grid 2 Accent 3"/><w:lsdException w:name="Medium Grid 3 Accent 3"/><w:lsdException w:name="Dark List Accent 3"/><w:lsdException w:name="Colorful Shading Accent 3"/><w:lsdException w:name="Colorful List Accent 3"/><w:lsdException w:name="Colorful Grid Accent 3"/><w:lsdException w:name="Light Shading Accent 4"/><w:lsdException w:name="Light List Accent 4"/><w:lsdException w:name="Light Grid Accent 4"/><w:lsdException w:name="Medium Shading 1 Accent 4"/><w:lsdException w:name="Medium Shading 2 Accent 4"/><w:lsdException w:name="Medium List 1 Accent 4"/><w:lsdException w:name="Medium List 2 Accent 4"/><w:lsdException w:name="Medium Grid 1 Accent 4"/><w:lsdException w:name="Medium Grid 2 Accent 4"/><w:lsdException w:name="Medium Grid 3 Accent 4"/><w:lsdException w:name="Dark List Accent 4"/><w:lsdException w:name="Colorful Shading Accent 4"/><w:lsdException w:name="Colorful List Accent 4"/><w:lsdException w:name="Colorful Grid Accent 4"/><w:lsdException w:name="Light Shading Accent 5"/><w:lsdException w:name="Light List Accent 5"/><w:lsdException w:name="Light Grid Accent 5"/><w:lsdException w:name="Medium Shading 1 Accent 5"/><w:lsdException w:name="Medium Shading 2 Accent 5"/><w:lsdException w:name="Medium List 1 Accent 5"/><w:lsdException w:name="Medium List 2 Accent 5"/><w:lsdException w:name="Medium Grid 1 Accent 5"/><w:lsdException w:name="Medium Grid 2 Accent 5"/><w:lsdException w:name="Medium Grid 3 Accent 5"/><w:lsdException w:name="Dark List Accent 5"/><w:lsdException w:name="Colorful Shading Accent 5"/><w:lsdException w:name="Colorful List Accent 5"/><w:lsdException w:name="Colorful Grid Accent 5"/><w:lsdException w:name="Light Shading Accent 6"/><w:lsdException w:name="Light List Accent 6"/><w:lsdException w:name="Light Grid Accent 6"/><w:lsdException w:name="Medium Shading 1 Accent 6"/><w:lsdException w:name="Medium Shading 2 Accent 6"/><w:lsdException w:name="Medium List 1 Accent 6"/><w:lsdException w:name="Medium List 2 Accent 6"/><w:lsdException w:name="Medium Grid 1 Accent 6"/><w:lsdException w:name="Medium Grid 2 Accent 6"/><w:lsdException w:name="Medium Grid 3 Accent 6"/><w:lsdException w:name="Dark List Accent 6"/><w:lsdException w:name="Colorful Shading Accent 6"/><w:lsdException w:name="Colorful List Accent 6"/><w:lsdException w:name="Colorful Grid Accent 6"/><w:lsdException w:name="Subtle Emphasis"/><w:lsdException w:name="Intense Emphasis"/><w:lsdException w:name="Subtle Reference"/><w:lsdException w:name="Intense Reference"/><w:lsdException w:name="Book Title"/><w:lsdException w:name="TOC Heading"/></w:latentStyles><w:style w:type="paragraph" w:default="on" w:styleId="Normal"><w:name w:val="Normal"/><w:rsid w:val="00BC18D8"/><w:pPr><w:spacing w:after="200" w:line="276" w:line-rule="auto"/></w:pPr><w:rPr><wx:font wx:val="Calibri"/><w:sz w:val="22"/><w:sz-cs w:val="22"/><w:lang w:val="VI" w:fareast="VI" w:bidi="AR-SA"/></w:rPr></w:style><w:style w:type="character" w:default="on" w:styleId="DefaultParagraphFont"><w:name w:val="Default Paragraph Font"/></w:style><w:style w:type="table" w:default="on" w:styleId="TableNormal"><w:name w:val="Normal Table"/><wx:uiName wx:val="Table Normal"/><w:rPr><wx:font wx:val="Calibri"/><w:lang w:val="EN-US" w:fareast="EN-US" w:bidi="AR-SA"/></w:rPr><w:tblPr><w:tblInd w:w="0" w:type="dxa"/><w:tblCellMar><w:top w:w="0" w:type="dxa"/><w:left w:w="108" w:type="dxa"/><w:bottom w:w="0" w:type="dxa"/><w:right w:w="108" w:type="dxa"/></w:tblCellMar></w:tblPr></w:style><w:style w:type="list" w:default="on" w:styleId="NoList"><w:name w:val="No List"/></w:style><w:style w:type="paragraph" w:styleId="Header"><w:name w:val="header"/><wx:uiName wx:val="Header"/><w:basedOn w:val="Normal"/><w:link w:val="HeaderChar"/><w:rsid w:val="00E352A4"/><w:pPr><w:tabs><w:tab w:val="center" w:pos="4680"/><w:tab w:val="right" w:pos="9360"/></w:tabs><w:spacing w:after="0" w:line="240" w:line-rule="auto"/></w:pPr><w:rPr><wx:font wx:val="Calibri"/></w:rPr></w:style><w:style w:type="character" w:styleId="HeaderChar"><w:name w:val="Header Char"/><w:basedOn w:val="DefaultParagraphFont"/><w:link w:val="Header"/><w:rsid w:val="00E352A4"/></w:style><w:style w:type="paragraph" w:styleId="Footer"><w:name w:val="footer"/><wx:uiName wx:val="Footer"/><w:basedOn w:val="Normal"/><w:link w:val="FooterChar"/><w:rsid w:val="00E352A4"/><w:pPr><w:tabs><w:tab w:val="center" w:pos="4680"/><w:tab w:val="right" w:pos="9360"/></w:tabs><w:spacing w:after="0" w:line="240" w:line-rule="auto"/></w:pPr><w:rPr><wx:font wx:val="Calibri"/></w:rPr></w:style><w:style w:type="character" w:styleId="FooterChar"><w:name w:val="Footer Char"/><w:basedOn w:val="DefaultParagraphFont"/><w:link w:val="Footer"/><w:rsid w:val="00E352A4"/></w:style><w:style w:type="table" w:styleId="TableGrid"><w:name w:val="Table Grid"/><w:basedOn w:val="TableNormal"/><w:rsid w:val="00ED4B5A"/><w:rPr><wx:font wx:val="Calibri"/></w:rPr><w:tblPr><w:tblBorders><w:top w:val="single" w:sz="4" wx:bdrwidth="10" w:space="0" w:color="000000"/><w:left w:val="single" w:sz="4" wx:bdrwidth="10" w:space="0" w:color="000000"/><w:bottom w:val="single" w:sz="4" wx:bdrwidth="10" w:space="0" w:color="000000"/><w:right w:val="single" w:sz="4" wx:bdrwidth="10" w:space="0" w:color="000000"/><w:insideH w:val="single" w:sz="4" wx:bdrwidth="10" w:space="0" w:color="000000"/><w:insideV w:val="single" w:sz="4" wx:bdrwidth="10" w:space="0" w:color="000000"/></w:tblBorders></w:tblPr></w:style><w:style w:type="paragraph" w:styleId="BalloonText"><w:name w:val="Balloon Text"/><w:basedOn w:val="Normal"/><w:link w:val="BalloonTextChar"/><w:rsid w:val="007E677D"/><w:pPr><w:spacing w:after="0" w:line="240" w:line-rule="auto"/></w:pPr><w:rPr><w:rFonts w:ascii="Tahoma" w:fareast="Times New Roman" w:h-ansi="Tahoma" w:cs="Tahoma"/><wx:font wx:val="Tahoma"/><w:sz w:val="16"/><w:sz-cs w:val="16"/></w:rPr></w:style><w:style w:type="character" w:styleId="BalloonTextChar"><w:name w:val="Balloon Text Char"/><w:link w:val="BalloonText"/><w:rsid w:val="007E677D"/><w:rPr><w:rFonts w:ascii="Tahoma" w:fareast="Times New Roman" w:h-ansi="Tahoma" w:cs="Tahoma"/><w:sz w:val="16"/><w:sz-cs w:val="16"/></w:rPr></w:style><w:style w:type="paragraph" w:styleId="NormalWeb"><w:name w:val="Normal (Web)"/><w:basedOn w:val="Normal"/><w:rsid w:val="007E677D"/><w:pPr><w:spacing w:before="100" w:before-autospacing="on" w:after="100" w:after-autospacing="on" w:line="240" w:line-rule="auto"/></w:pPr><w:rPr><w:rFonts w:ascii="Times New Roman" w:fareast="Times New Roman" w:h-ansi="Times New Roman"/><wx:font wx:val="Times New Roman"/><w:sz w:val="24"/><w:sz-cs w:val="24"/></w:rPr></w:style></w:styles><w:divs><w:div w:id="352415208"><w:bodyDiv w:val="on"/><w:marLeft w:val="0"/><w:marRight w:val="0"/><w:marTop w:val="0"/><w:marBottom w:val="0"/><w:divBdr><w:top w:val="none" w:sz="0" wx:bdrwidth="0" w:space="0" w:color="auto"/><w:left w:val="none" w:sz="0" wx:bdrwidth="0" w:space="0" w:color="auto"/><w:bottom w:val="none" w:sz="0" wx:bdrwidth="0" w:space="0" w:color="auto"/><w:right w:val="none" w:sz="0" wx:bdrwidth="0" w:space="0" w:color="auto"/></w:divBdr></w:div></w:divs><w:shapeDefaults><o:shapedefaults v:ext="edit" spidmax="1026"/><o:shapelayout v:ext="edit"><o:idmap v:ext="edit" data="1"/></o:shapelayout></w:shapeDefaults><w:docPr><w:view w:val="print"/><w:zoom w:percent="90"/><w:doNotEmbedSystemFonts/><w:proofState w:spelling="clean" w:grammar="clean"/><w:defaultTabStop w:val="720"/><w:punctuationKerning/><w:characterSpacingControl w:val="DontCompress"/><w:optimizeForBrowser/><w:relyOnVML/><w:validateAgainstSchema/><w:saveInvalidXML w:val="off"/><w:ignoreMixedContent w:val="off"/><w:alwaysShowPlaceholderText w:val="off"/><w:footnotePr><w:footnote w:type="separator"><w:p wsp:rsidR="00290AA6" wsp:rsidRDefault="00290AA6" wsp:rsidP="00E352A4"><w:pPr><w:spacing w:after="0" w:line="240" w:line-rule="auto"/></w:pPr><w:r><w:separator/></w:r></w:p></w:footnote><w:footnote w:type="continuation-separator"><w:p wsp:rsidR="00290AA6" wsp:rsidRDefault="00290AA6" wsp:rsidP="00E352A4"><w:pPr><w:spacing w:after="0" w:line="240" w:line-rule="auto"/></w:pPr><w:r><w:continuationSeparator/></w:r></w:p></w:footnote></w:footnotePr><w:endnotePr><w:endnote w:type="separator"><w:p wsp:rsidR="00290AA6" wsp:rsidRDefault="00290AA6" wsp:rsidP="00E352A4"><w:pPr><w:spacing w:after="0" w:line="240" w:line-rule="auto"/></w:pPr><w:r><w:separator/></w:r></w:p></w:endnote><w:endnote w:type="continuation-separator"><w:p wsp:rsidR="00290AA6" wsp:rsidRDefault="00290AA6" wsp:rsidP="00E352A4"><w:pPr><w:spacing w:after="0" w:line="240" w:line-rule="auto"/></w:pPr><w:r><w:continuationSeparator/></w:r></w:p></w:endnote></w:endnotePr><w:compat><w:breakWrappedTables/><w:snapToGridInCell/><w:wrapTextWithPunct/><w:useAsianBreakRules/><w:dontGrowAutofit/></w:compat><wsp:rsids><wsp:rsidRoot wsp:val="000B002A"/><wsp:rsid wsp:val="00005CDC"/><wsp:rsid wsp:val="00020DB4"/><wsp:rsid wsp:val="00023C5A"/><wsp:rsid wsp:val="00023F6E"/><wsp:rsid wsp:val="00063A6A"/><wsp:rsid wsp:val="00063BF0"/><wsp:rsid wsp:val="00071670"/><wsp:rsid wsp:val="000812CF"/><wsp:rsid wsp:val="00081F96"/><wsp:rsid wsp:val="000B002A"/><wsp:rsid wsp:val="000B2744"/><wsp:rsid wsp:val="000C5754"/><wsp:rsid wsp:val="000E44DB"/><wsp:rsid wsp:val="00120C63"/><wsp:rsid wsp:val="001609BE"/><wsp:rsid wsp:val="001879A2"/><wsp:rsid wsp:val="0019306B"/><wsp:rsid wsp:val="00195043"/><wsp:rsid wsp:val="001D3E27"/><wsp:rsid wsp:val="001D49BB"/><wsp:rsid wsp:val="001F198B"/><wsp:rsid wsp:val="002009D0"/><wsp:rsid wsp:val="002059F0"/><wsp:rsid wsp:val="00206E2D"/><wsp:rsid wsp:val="002227ED"/><wsp:rsid wsp:val="00233CD0"/><wsp:rsid wsp:val="00235B40"/><wsp:rsid wsp:val="00235F74"/><wsp:rsid wsp:val="00241A9D"/><wsp:rsid wsp:val="00243AF5"/><wsp:rsid wsp:val="0025169D"/><wsp:rsid wsp:val="00260AF3"/><wsp:rsid wsp:val="00266E5D"/><wsp:rsid wsp:val="00290AA6"/><wsp:rsid wsp:val="002964A6"/><wsp:rsid wsp:val="002A6F6D"/><wsp:rsid wsp:val="002B5BFB"/><wsp:rsid wsp:val="0030498F"/><wsp:rsid wsp:val="00311724"/><wsp:rsid wsp:val="00326EC5"/><wsp:rsid wsp:val="00346B30"/><wsp:rsid wsp:val="003504EA"/><wsp:rsid wsp:val="0035215C"/><wsp:rsid wsp:val="003867D0"/><wsp:rsid wsp:val="00393C57"/><wsp:rsid wsp:val="003A5212"/><wsp:rsid wsp:val="003B0779"/><wsp:rsid wsp:val="003C0365"/><wsp:rsid wsp:val="003E1EF4"/><wsp:rsid wsp:val="003F7EDA"/><wsp:rsid wsp:val="00406A7B"/><wsp:rsid wsp:val="0042121F"/><wsp:rsid wsp:val="004225E8"/><wsp:rsid wsp:val="0042390A"/><wsp:rsid wsp:val="0044796A"/><wsp:rsid wsp:val="00451367"/><wsp:rsid wsp:val="00475AA1"/><wsp:rsid wsp:val="00490B2A"/><wsp:rsid wsp:val="00490DEB"/><wsp:rsid wsp:val="004C2D4E"/><wsp:rsid wsp:val="004D0CE3"/><wsp:rsid wsp:val="004D5E89"/><wsp:rsid wsp:val="004F1EDE"/><wsp:rsid wsp:val="004F60AF"/><wsp:rsid wsp:val="005101D5"/><wsp:rsid wsp:val="005112DC"/><wsp:rsid wsp:val="005115E6"/><wsp:rsid wsp:val="005273AB"/><wsp:rsid wsp:val="005455FD"/><wsp:rsid wsp:val="00554577"/><wsp:rsid wsp:val="00570C98"/><wsp:rsid wsp:val="00583720"/><wsp:rsid wsp:val="005A2F0E"/><wsp:rsid wsp:val="005A34B4"/><wsp:rsid wsp:val="005A3DBD"/><wsp:rsid wsp:val="005D2866"/><wsp:rsid wsp:val="005D5234"/><wsp:rsid wsp:val="005E376B"/><wsp:rsid wsp:val="005F5FD5"/><wsp:rsid wsp:val="00612BBA"/><wsp:rsid wsp:val="006355E6"/><wsp:rsid wsp:val="00642331"/><wsp:rsid wsp:val="00642886"/><wsp:rsid wsp:val="00645512"/><wsp:rsid wsp:val="006500A2"/><wsp:rsid wsp:val="006503F2"/><wsp:rsid wsp:val="00666E1F"/><wsp:rsid wsp:val="006904E8"/><wsp:rsid wsp:val="006B1DBD"/><wsp:rsid wsp:val="006E735B"/><wsp:rsid wsp:val="00711851"/><wsp:rsid wsp:val="007153FB"/><wsp:rsid wsp:val="00730B04"/><wsp:rsid wsp:val="0073458A"/><wsp:rsid wsp:val="007505CC"/><wsp:rsid wsp:val="00761F8C"/><wsp:rsid wsp:val="00766307"/><wsp:rsid wsp:val="0077115F"/><wsp:rsid wsp:val="00784066"/><wsp:rsid wsp:val="00797C90"/><wsp:rsid wsp:val="007B4C70"/><wsp:rsid wsp:val="007D5F3D"/><wsp:rsid wsp:val="007D6BCB"/><wsp:rsid wsp:val="007E1DAD"/><wsp:rsid wsp:val="007E1FF5"/><wsp:rsid wsp:val="007E677D"/><wsp:rsid wsp:val="007E762D"/><wsp:rsid wsp:val="0082013E"/><wsp:rsid wsp:val="008211C4"/><wsp:rsid wsp:val="0083093D"/><wsp:rsid wsp:val="008470AD"/><wsp:rsid wsp:val="00855E11"/><wsp:rsid wsp:val="008673DD"/><wsp:rsid wsp:val="008727F2"/><wsp:rsid wsp:val="00876F5F"/><wsp:rsid wsp:val="008A2C61"/><wsp:rsid wsp:val="009129BD"/><wsp:rsid wsp:val="00931457"/><wsp:rsid wsp:val="00944043"/><wsp:rsid wsp:val="0095304F"/><wsp:rsid wsp:val="00957D15"/><wsp:rsid wsp:val="00970C4E"/><wsp:rsid wsp:val="00985274"/><wsp:rsid wsp:val="009940E5"/><wsp:rsid wsp:val="009A4DE4"/><wsp:rsid wsp:val="009B2E55"/><wsp:rsid wsp:val="009C41ED"/><wsp:rsid wsp:val="009D3B1B"/><wsp:rsid wsp:val="00A31403"/><wsp:rsid wsp:val="00A354B8"/><wsp:rsid wsp:val="00A41C81"/><wsp:rsid wsp:val="00A91A17"/><wsp:rsid wsp:val="00AC163E"/><wsp:rsid wsp:val="00AC330D"/><wsp:rsid wsp:val="00AD334D"/><wsp:rsid wsp:val="00AF1CC9"/><wsp:rsid wsp:val="00AF4B90"/><wsp:rsid wsp:val="00AF58C1"/><wsp:rsid wsp:val="00B03842"/><wsp:rsid wsp:val="00B210C7"/><wsp:rsid wsp:val="00B26AC1"/><wsp:rsid wsp:val="00B53DA8"/><wsp:rsid wsp:val="00B92EBF"/><wsp:rsid wsp:val="00BA271A"/><wsp:rsid wsp:val="00BB5B68"/><wsp:rsid wsp:val="00BC18D8"/><wsp:rsid wsp:val="00BD0CD6"/><wsp:rsid wsp:val="00C0087A"/><wsp:rsid wsp:val="00C203E3"/><wsp:rsid wsp:val="00C20652"/><wsp:rsid wsp:val="00C54845"/><wsp:rsid wsp:val="00C73742"/><wsp:rsid wsp:val="00C75087"/><wsp:rsid wsp:val="00C7682E"/><wsp:rsid wsp:val="00C80792"/><wsp:rsid wsp:val="00C82F2A"/><wsp:rsid wsp:val="00C851B2"/><wsp:rsid wsp:val="00C90E8D"/><wsp:rsid wsp:val="00C9742D"/><wsp:rsid wsp:val="00CC2510"/><wsp:rsid wsp:val="00CC2803"/><wsp:rsid wsp:val="00CD1402"/><wsp:rsid wsp:val="00CF7F7A"/><wsp:rsid wsp:val="00D04B4B"/><wsp:rsid wsp:val="00D13D24"/><wsp:rsid wsp:val="00D16593"/><wsp:rsid wsp:val="00D35980"/><wsp:rsid wsp:val="00D372D2"/><wsp:rsid wsp:val="00D72062"/><wsp:rsid wsp:val="00D7615A"/><wsp:rsid wsp:val="00E13877"/><wsp:rsid wsp:val="00E165B2"/><wsp:rsid wsp:val="00E22445"/><wsp:rsid wsp:val="00E35159"/><wsp:rsid wsp:val="00E352A4"/><wsp:rsid wsp:val="00E56C16"/><wsp:rsid wsp:val="00E655D8"/><wsp:rsid wsp:val="00E66764"/><wsp:rsid wsp:val="00E8390F"/><wsp:rsid wsp:val="00E84323"/><wsp:rsid wsp:val="00E84546"/><wsp:rsid wsp:val="00E967DA"/><wsp:rsid wsp:val="00EA49F0"/><wsp:rsid wsp:val="00EB07FF"/><wsp:rsid wsp:val="00ED1708"/><wsp:rsid wsp:val="00ED4B5A"/><wsp:rsid wsp:val="00ED654E"/><wsp:rsid wsp:val="00EE3500"/><wsp:rsid wsp:val="00EE54A6"/><wsp:rsid wsp:val="00EE5B22"/><wsp:rsid wsp:val="00F032D5"/><wsp:rsid wsp:val="00F05624"/><wsp:rsid wsp:val="00F117DE"/><wsp:rsid wsp:val="00F22E25"/><wsp:rsid wsp:val="00F23604"/><wsp:rsid wsp:val="00F25B71"/><wsp:rsid wsp:val="00F275D0"/><wsp:rsid wsp:val="00F5106D"/><wsp:rsid wsp:val="00F53F01"/><wsp:rsid wsp:val="00F77EB6"/><wsp:rsid wsp:val="00F90B4F"/><wsp:rsid wsp:val="00F918DA"/><wsp:rsid wsp:val="00F9487C"/><wsp:rsid wsp:val="00FA45A8"/><wsp:rsid wsp:val="00FA712C"/><wsp:rsid wsp:val="00FC79EC"/><wsp:rsid wsp:val="00FC7B6F"/><wsp:rsid wsp:val="00FD5511"/><wsp:rsid wsp:val="00FD566F"/><wsp:rsid wsp:val="00FE1F0E"/><wsp:rsid wsp:val="00FF387D"/><wsp:rsid wsp:val="00FF3ABE"/><wsp:rsid wsp:val="00FF4BB9"/><wsp:rsid wsp:val="00FF6AC6"/></wsp:rsids></w:docPr><w:body><wx:sect><w:tbl><w:tblPr><w:tblW w:w="9922" w:type="dxa"/><w:tblInd w:w="108" w:type="dxa"/></w:tblPr><w:tblGrid><w:gridCol w:w="7087"/><w:gridCol w:w="2835"/></w:tblGrid><w:tr wsp:rsidR="00554577" wsp:rsidRPr="00B4325B" wsp:rsidTr="001F198B"><w:trPr><w:trHeight w:val="980"/></w:trPr><w:tc><w:tcPr><w:tcW w:w="7087" w:type="dxa"/><w:vAlign w:val="center"/></w:tcPr><aml:annotation aml:id="0" w:type="Word.Bookmark.Start" w:name="_Hlk85288360"/><w:p wsp:rsidR="00554577" wsp:rsidRPr="00C20652" wsp:rsidRDefault="00E84323" wsp:rsidP="00434EE9"><w:pPr><w:pStyle w:val="NormalWeb"/><w:spacing w:before="0" w:before-autospacing="off" w:after="0" w:after-autospacing="off" w:line="276" w:line-rule="auto"/><w:ind w:right="-18"/><w:rPr><w:b/><w:i/></w:rPr></w:pPr><w:r wsp:rsidRPr="00C20652"><w:rPr><w:b/><w:i/></w:rPr><w:fldChar w:fldCharType="begin"/></w:r><w:r wsp:rsidR="00554577" wsp:rsidRPr="00C20652"><w:rPr><w:b/><w:i/></w:rPr><w:instrText> MERGEFIELD  BTEN </w:instrText></w:r><w:r wsp:rsidRPr="00C20652"><w:rPr><w:b/><w:i/></w:rPr><w:fldChar w:fldCharType="separate"/></w:r><w:r wsp:rsidR="00554577" wsp:rsidRPr="00C20652"><w:rPr><w:b/><w:i/><w:noProof/></w:rPr><w:t>«BTEN»</w:t></w:r><w:r wsp:rsidRPr="00C20652"><w:rPr><w:b/><w:i/></w:rPr><w:fldChar w:fldCharType="end"/></w:r></w:p><w:p wsp:rsidR="00554577" wsp:rsidRPr="004A7994" wsp:rsidRDefault="00E84323" wsp:rsidP="00434EE9"><w:pPr><w:pStyle w:val="NormalWeb"/><w:spacing w:before="0" w:before-autospacing="off" w:after="0" w:after-autospacing="off" w:line="276" w:line-rule="auto"/><w:ind w:right="-18"/><w:rPr><w:b/><w:i/></w:rPr></w:pPr><w:r wsp:rsidRPr="00C20652"><w:rPr><w:b/><w:i/></w:rPr><w:fldChar w:fldCharType="begin"/></w:r><w:r wsp:rsidR="00554577" wsp:rsidRPr="00C20652"><w:rPr><w:b/><w:i/></w:rPr><w:instrText> MERGEFIELD  BDCHI </w:instrText></w:r><w:r wsp:rsidRPr="00C20652"><w:rPr><w:b/><w:i/></w:rPr><w:fldChar w:fldCharType="separate"/></w:r><w:r wsp:rsidR="00554577" wsp:rsidRPr="00C20652"><w:rPr><w:b/><w:i/><w:noProof/></w:rPr><w:t>«BDCHI»</w:t></w:r><w:r wsp:rsidRPr="00C20652"><w:rPr><w:b/><w:i/></w:rPr><w:fldChar w:fldCharType="end"/></w:r></w:p></w:tc><w:tc><w:tcPr><w:tcW w:w="2835" w:type="dxa"/><w:vAlign w:val="center"/></w:tcPr><w:p wsp:rsidR="00554577" wsp:rsidRPr="00A40562" wsp:rsidRDefault="00554577" wsp:rsidP="00434EE9"><w:pPr><w:pStyle w:val="NormalWeb"/><w:spacing w:before="0" w:before-autospacing="off" w:after="0" w:after-autospacing="off"/><w:ind w:right="-18"/><w:jc w:val="center"/><w:rPr><w:b/></w:rPr></w:pPr><w:r wsp:rsidRPr="00C978B5"><w:rPr><w:b/></w:rPr><w:t>PSOURCE_LOGO</w:t></w:r></w:p></w:tc></w:tr><aml:annotation aml:id="0" w:type="Word.Bookmark.End"/></w:tbl><w:p wsp:rsidR="007E677D" wsp:rsidRDefault="007E677D"/><w:tbl><w:tblPr><w:tblW w:w="10206" w:type="dxa"/><w:tblInd w:w="108" w:type="dxa"/><w:tblLayout w:type="Fixed"/><w:tblLook w:val="04A0"/></w:tblPr><w:tblGrid><w:gridCol w:w="851"/><w:gridCol w:w="619"/><w:gridCol w:w="150"/><w:gridCol w:w="86"/><w:gridCol w:w="2435"/><w:gridCol w:w="1529"/><w:gridCol w:w="13"/><w:gridCol w:w="352"/><w:gridCol w:w="1620"/><w:gridCol w:w="2268"/><w:gridCol w:w="283"/></w:tblGrid><w:tr wsp:rsidR="000B002A" wsp:rsidRPr="00E352A4" wsp:rsidTr="005273AB"><w:trPr><w:gridAfter w:val="1"/><w:wAfter w:w="283" w:type="dxa"/><w:trHeight w:val="170"/></w:trPr><w:tc><w:tcPr><w:tcW w:w="9923" w:type="dxa"/><w:gridSpan w:val="10"/><w:noWrap/><w:vAlign w:val="center"/></w:tcPr><w:p wsp:rsidR="000B002A" wsp:rsidRDefault="000B002A" wsp:rsidP="000B002A"><w:pPr><w:spacing w:after="0" w:line="240" w:line-rule="auto"/><w:jc w:val="center"/><w:rPr><w:rFonts w:ascii="Times New Roman" w:fareast="Times New Roman" w:h-ansi="Times New Roman"/><wx:font wx:val="Times New Roman"/><w:b/><w:b-cs/><w:sz w:val="28"/><w:sz-cs w:val="28"/></w:rPr></w:pPr><w:r wsp:rsidRPr="000B002A"><w:rPr><w:rFonts w:ascii="Times New Roman" w:fareast="Times New Roman" w:h-ansi="Times New Roman"/><wx:font wx:val="Times New Roman"/><w:b/><w:b-cs/><w:sz w:val="28"/><w:sz-cs w:val="28"/></w:rPr><w:t>BIÊN BẢN BÀN GIAO HỒ SƠ XE CƠ GIỚI</w:t></w:r></w:p><w:p wsp:rsidR="009B2E55" wsp:rsidRPr="009B2E55" wsp:rsidRDefault="009B2E55" wsp:rsidP="009B2E55"><w:pPr><w:spacing w:after="0"/><w:jc w:val="center"/><w:rPr><w:rFonts w:ascii="Times New Roman" w:fareast="Times New Roman" w:h-ansi="Times New Roman"/><wx:font wx:val="Times New Roman"/><w:i/><w:i-cs/><w:sz w:val="24"/><w:sz-cs w:val="24"/></w:rPr></w:pPr><w:r wsp:rsidRPr="009B2E55"><w:rPr><w:rFonts w:ascii="Times New Roman" w:fareast="Times New Roman" w:h-ansi="Times New Roman"/><wx:font wx:val="Times New Roman"/><w:i/><w:i-cs/><w:sz w:val="28"/><w:sz-cs w:val="28"/></w:rPr><w:t>(</w:t></w:r><w:r wsp:rsidRPr="009B2E55"><w:rPr><w:rFonts w:ascii="Times New Roman" w:fareast="Times New Roman" w:h-ansi="Times New Roman"/><wx:font wx:val="Times New Roman"/><w:i/><w:i-cs/><w:sz w:val="24"/><w:sz-cs w:val="24"/></w:rPr><w:t>Số hồ sơ: </w:t></w:r><w:r wsp:rsidR="00E84323" wsp:rsidRPr="009B2E55"><w:rPr><w:rFonts w:ascii="Times New Roman" w:fareast="Times New Roman" w:h-ansi="Times New Roman"/><wx:font wx:val="Times New Roman"/><w:i/><w:i-cs/><w:sz w:val="24"/><w:sz-cs w:val="24"/></w:rPr><w:fldChar w:fldCharType="begin"/></w:r><w:r wsp:rsidRPr="009B2E55"><w:rPr><w:rFonts w:ascii="Times New Roman" w:fareast="Times New Roman" w:h-ansi="Times New Roman"/><wx:font wx:val="Times New Roman"/><w:i/><w:i-cs/><w:sz w:val="24"/><w:sz-cs w:val="24"/></w:rPr><w:instrText> MERGEFIELD  CSO_HS </w:instrText></w:r><w:r wsp:rsidR="00E84323" wsp:rsidRPr="009B2E55"><w:rPr><w:rFonts w:ascii="Times New Roman" w:fareast="Times New Roman" w:h-ansi="Times New Roman"/><wx:font wx:val="Times New Roman"/><w:i/><w:i-cs/><w:sz w:val="24"/><w:sz-cs w:val="24"/></w:rPr><w:fldChar w:fldCharType="separate"/></w:r><w:r wsp:rsidRPr="009B2E55"><w:rPr><w:rFonts w:ascii="Times New Roman" w:fareast="Times New Roman" w:h-ansi="Times New Roman"/><wx:font wx:val="Times New Roman"/><w:i/><w:i-cs/><w:noProof/><w:sz w:val="24"/><w:sz-cs w:val="24"/></w:rPr><w:t>«CSO_HS»</w:t></w:r><w:r wsp:rsidR="00E84323" wsp:rsidRPr="009B2E55"><w:rPr><w:rFonts w:ascii="Times New Roman" w:fareast="Times New Roman" w:h-ansi="Times New Roman"/><wx:font wx:val="Times New Roman"/><w:i/><w:i-cs/><w:sz w:val="24"/><w:sz-cs w:val="24"/></w:rPr><w:fldChar w:fldCharType="end"/></w:r><w:r wsp:rsidRPr="009B2E55"><w:rPr><w:rFonts w:ascii="Times New Roman" w:fareast="Times New Roman" w:h-ansi="Times New Roman"/><wx:font wx:val="Times New Roman"/><w:i/><w:i-cs/><w:sz w:val="24"/><w:sz-cs w:val="24"/></w:rPr><w:t>)</w:t></w:r></w:p><w:p wsp:rsidR="003F7EDA" wsp:rsidRPr="000B002A" wsp:rsidRDefault="003F7EDA" wsp:rsidP="009B2E55"><w:pPr><w:spacing w:after="0"/><w:jc w:val="center"/><w:rPr><w:rFonts w:ascii="Times New Roman" w:fareast="Times New Roman" w:h-ansi="Times New Roman"/><wx:font wx:val="Times New Roman"/><w:b/><w:b-cs/><w:sz w:val="28"/><w:sz-cs w:val="28"/></w:rPr></w:pPr></w:p></w:tc></w:tr><w:tr wsp:rsidR="00A354B8" wsp:rsidRPr="00C20652" wsp:rsidTr="005273AB"><w:trPr><w:gridAfter w:val="1"/><w:wAfter w:w="283" w:type="dxa"/><w:trHeight w:val="170"/></w:trPr><w:tc><w:tcPr><w:tcW w:w="1620" w:type="dxa"/><w:gridSpan w:val="3"/><w:noWrap/><w:vAlign w:val="bottom"/></w:tcPr><w:p wsp:rsidR="00A354B8" wsp:rsidRPr="004D5E89" wsp:rsidRDefault="00A354B8" wsp:rsidP="002227ED"><w:pPr><w:spacing w:before="60" w:after="60"/><w:ind w:hanging="108"/><w:rPr><w:rFonts w:ascii="Times New Roman" w:fareast="Times New Roman" w:h-ansi="Times New Roman"/><wx:font wx:val="Times New Roman"/><w:sz w:val="24"/><w:sz-cs w:val="24"/></w:rPr></w:pPr><w:r wsp:rsidRPr="004D5E89"><w:rPr><w:rFonts w:ascii="Times New Roman" w:fareast="Times New Roman" w:h-ansi="Times New Roman"/><wx:font wx:val="Times New Roman"/><w:sz w:val="24"/><w:sz-cs w:val="24"/></w:rPr><w:t>Tên chủ xe</w:t></w:r></w:p></w:tc><w:tc><w:tcPr><w:tcW w:w="8303" w:type="dxa"/><w:gridSpan w:val="7"/><w:noWrap/><w:vAlign w:val="bottom"/></w:tcPr><w:p wsp:rsidR="00A354B8" wsp:rsidRPr="004D5E89" wsp:rsidRDefault="004D5E89" wsp:rsidP="005273AB"><w:pPr><w:spacing w:before="60" w:after="60"/><w:ind w:left="-132"/><w:rPr><w:rFonts w:ascii="Times New Roman" w:fareast="Times New Roman" w:h-ansi="Times New Roman"/><wx:font wx:val="Times New Roman"/><w:sz w:val="24"/><w:sz-cs w:val="24"/></w:rPr></w:pPr><w:r wsp:rsidRPr="004D5E89"><w:rPr><w:rFonts w:ascii="Times New Roman" w:fareast="Times New Roman" w:h-ansi="Times New Roman"/><wx:font wx:val="Times New Roman"/><w:sz w:val="24"/><w:sz-cs w:val="24"/></w:rPr><w:t>:</w:t></w:r><w:r wsp:rsidR="00A354B8" wsp:rsidRPr="004D5E89"><w:rPr><w:rFonts w:ascii="Times New Roman" w:fareast="Times New Roman" w:h-ansi="Times New Roman"/><wx:font wx:val="Times New Roman"/><w:sz w:val="24"/><w:sz-cs w:val="24"/></w:rPr><w:t> </w:t></w:r><w:r wsp:rsidR="00E84323" wsp:rsidRPr="004D5E89"><w:rPr><w:rFonts w:ascii="Times New Roman" w:h-ansi="Times New Roman"/><wx:font wx:val="Times New Roman"/><w:sz w:val="24"/><w:sz-cs w:val="24"/></w:rPr><w:fldChar w:fldCharType="begin"/></w:r><w:r wsp:rsidR="00730B04" wsp:rsidRPr="004D5E89"><w:rPr><w:rFonts w:ascii="Times New Roman" w:h-ansi="Times New Roman"/><wx:font wx:val="Times New Roman"/><w:sz w:val="24"/><w:sz-cs w:val="24"/></w:rPr><w:instrText> MERGEFIELD  CCHU_XE </w:instrText></w:r><w:r wsp:rsidR="00E84323" wsp:rsidRPr="004D5E89"><w:rPr><w:rFonts w:ascii="Times New Roman" w:h-ansi="Times New Roman"/><wx:font wx:val="Times New Roman"/><w:sz w:val="24"/><w:sz-cs w:val="24"/></w:rPr><w:fldChar w:fldCharType="separate"/></w:r><w:r wsp:rsidR="00730B04" wsp:rsidRPr="004D5E89"><w:rPr><w:rFonts w:ascii="Times New Roman" w:h-ansi="Times New Roman"/><wx:font wx:val="Times New Roman"/><w:noProof/><w:sz w:val="24"/><w:sz-cs w:val="24"/></w:rPr><w:t>«CCHU_XE»</w:t></w:r><w:r wsp:rsidR="00E84323" wsp:rsidRPr="004D5E89"><w:rPr><w:rFonts w:ascii="Times New Roman" w:h-ansi="Times New Roman"/><wx:font wx:val="Times New Roman"/><w:sz w:val="24"/><w:sz-cs w:val="24"/></w:rPr><w:fldChar w:fldCharType="end"/></w:r></w:p></w:tc></w:tr><w:tr wsp:rsidR="00B26AC1" wsp:rsidRPr="00C20652" wsp:rsidTr="005273AB"><w:trPr><w:gridAfter w:val="1"/><w:wAfter w:w="283" w:type="dxa"/><w:trHeight w:val="170"/></w:trPr><w:tc><w:tcPr><w:tcW w:w="1620" w:type="dxa"/><w:gridSpan w:val="3"/><w:noWrap/><w:vAlign w:val="bottom"/></w:tcPr><w:p wsp:rsidR="00B26AC1" wsp:rsidRPr="004D5E89" wsp:rsidRDefault="00B26AC1" wsp:rsidP="002227ED"><w:pPr><w:spacing w:before="60" w:after="60"/><w:ind w:left="-108"/><w:rPr><w:rFonts w:ascii="Times New Roman" w:fareast="Times New Roman" w:h-ansi="Times New Roman"/><wx:font wx:val="Times New Roman"/><w:sz w:val="24"/><w:sz-cs w:val="24"/></w:rPr></w:pPr><w:r wsp:rsidRPr="004D5E89"><w:rPr><w:rFonts w:ascii="Times New Roman" w:fareast="Times New Roman" w:h-ansi="Times New Roman"/><wx:font wx:val="Times New Roman"/><w:sz w:val="24"/><w:sz-cs w:val="24"/></w:rPr><w:t>Biển kiểm soát</w:t></w:r></w:p></w:tc><w:tc><w:tcPr><w:tcW w:w="8303" w:type="dxa"/><w:gridSpan w:val="7"/><w:noWrap/><w:vAlign w:val="bottom"/></w:tcPr><w:p wsp:rsidR="00B26AC1" wsp:rsidRPr="004D5E89" wsp:rsidRDefault="00B26AC1" wsp:rsidP="002227ED"><w:pPr><w:spacing w:before="60" w:after="60"/><w:ind w:left="-127"/><w:rPr><w:rFonts w:ascii="Times New Roman" w:fareast="Times New Roman" w:h-ansi="Times New Roman"/><wx:font wx:val="Times New Roman"/><w:sz w:val="24"/><w:sz-cs w:val="24"/></w:rPr></w:pPr><w:r wsp:rsidRPr="004D5E89"><w:rPr><w:rFonts w:ascii="Times New Roman" w:h-ansi="Times New Roman"/><wx:font wx:val="Times New Roman"/><w:sz w:val="24"/><w:sz-cs w:val="24"/></w:rPr><w:t>: </w:t></w:r><w:r wsp:rsidR="00E84323" wsp:rsidRPr="004D5E89"><w:rPr><w:rFonts w:ascii="Times New Roman" w:h-ansi="Times New Roman"/><wx:font wx:val="Times New Roman"/><w:sz w:val="24"/><w:sz-cs w:val="24"/></w:rPr><w:fldChar w:fldCharType="begin"/></w:r><w:r wsp:rsidRPr="004D5E89"><w:rPr><w:rFonts w:ascii="Times New Roman" w:h-ansi="Times New Roman"/><wx:font wx:val="Times New Roman"/><w:sz w:val="24"/><w:sz-cs w:val="24"/></w:rPr><w:instrText> MERGEFIELD  CDOI_TUONG </w:instrText></w:r><w:r wsp:rsidR="00E84323" wsp:rsidRPr="004D5E89"><w:rPr><w:rFonts w:ascii="Times New Roman" w:h-ansi="Times New Roman"/><wx:font wx:val="Times New Roman"/><w:sz w:val="24"/><w:sz-cs w:val="24"/></w:rPr><w:fldChar w:fldCharType="separate"/></w:r><w:r wsp:rsidRPr="004D5E89"><w:rPr><w:rFonts w:ascii="Times New Roman" w:h-ansi="Times New Roman"/><wx:font wx:val="Times New Roman"/><w:noProof/><w:sz w:val="24"/><w:sz-cs w:val="24"/></w:rPr><w:t>«CDOI_TUONG»</w:t></w:r><w:r wsp:rsidR="00E84323" wsp:rsidRPr="004D5E89"><w:rPr><w:rFonts w:ascii="Times New Roman" w:h-ansi="Times New Roman"/><wx:font wx:val="Times New Roman"/><w:sz w:val="24"/><w:sz-cs w:val="24"/></w:rPr><w:fldChar w:fldCharType="end"/></w:r><w:r wsp:rsidRPr="004D5E89"><w:rPr><w:rFonts w:ascii="Times New Roman" w:h-ansi="Times New Roman"/><wx:font wx:val="Times New Roman"/><w:color w:val="000000"/><w:sz w:val="24"/><w:sz-cs w:val="24"/></w:rPr><w:t> </w:t></w:r></w:p></w:tc></w:tr><w:tr wsp:rsidR="000B002A" wsp:rsidRPr="00C20652" wsp:rsidTr="005273AB"><w:trPr><w:trHeight w:val="170"/></w:trPr><w:tc><w:tcPr><w:tcW w:w="851" w:type="dxa"/><w:tcBorders><w:bottom w:val="single" w:sz="4" wx:bdrwidth="10" w:space="0" w:color="auto"/></w:tcBorders><w:noWrap/><w:vAlign w:val="bottom"/></w:tcPr><w:p wsp:rsidR="000B002A" wsp:rsidRPr="00C20652" wsp:rsidRDefault="000B002A" wsp:rsidP="000B002A"><w:pPr><w:spacing w:after="0" w:line="240" w:line-rule="auto"/><w:rPr><w:rFonts w:ascii="Times New Roman" w:fareast="Times New Roman" w:h-ansi="Times New Roman"/><wx:font wx:val="Times New Roman"/><w:sz w:val="24"/><w:sz-cs w:val="24"/></w:rPr></w:pPr><w:r wsp:rsidRPr="00C20652"><w:rPr><w:rFonts w:ascii="Times New Roman" w:fareast="Times New Roman" w:h-ansi="Times New Roman"/><wx:font wx:val="Times New Roman"/><w:sz w:val="24"/><w:sz-cs w:val="24"/></w:rPr><w:t> </w:t></w:r></w:p></w:tc><w:tc><w:tcPr><w:tcW w:w="619" w:type="dxa"/><w:tcBorders><w:bottom w:val="single" w:sz="4" wx:bdrwidth="10" w:space="0" w:color="auto"/></w:tcBorders><w:noWrap/><w:vAlign w:val="bottom"/></w:tcPr><w:p wsp:rsidR="000B002A" wsp:rsidRPr="00C20652" wsp:rsidRDefault="000B002A" wsp:rsidP="000B002A"><w:pPr><w:spacing w:after="0" w:line="240" w:line-rule="auto"/><w:jc w:val="center"/><w:rPr><w:rFonts w:ascii="Times New Roman" w:fareast="Times New Roman" w:h-ansi="Times New Roman"/><wx:font wx:val="Times New Roman"/><w:sz w:val="24"/><w:sz-cs w:val="24"/></w:rPr></w:pPr><w:r wsp:rsidRPr="00C20652"><w:rPr><w:rFonts w:ascii="Times New Roman" w:fareast="Times New Roman" w:h-ansi="Times New Roman"/><wx:font wx:val="Times New Roman"/><w:sz w:val="24"/><w:sz-cs w:val="24"/></w:rPr><w:t> </w:t></w:r></w:p></w:tc><w:tc><w:tcPr><w:tcW w:w="236" w:type="dxa"/><w:gridSpan w:val="2"/><w:tcBorders><w:bottom w:val="single" w:sz="4" wx:bdrwidth="10" w:space="0" w:color="auto"/></w:tcBorders><w:noWrap/><w:vAlign w:val="bottom"/></w:tcPr><w:p wsp:rsidR="000B002A" wsp:rsidRPr="00C20652" wsp:rsidRDefault="000B002A" wsp:rsidP="000B002A"><w:pPr><w:spacing w:after="0" w:line="240" w:line-rule="auto"/><w:rPr><w:rFonts w:ascii="Times New Roman" w:fareast="Times New Roman" w:h-ansi="Times New Roman"/><wx:font wx:val="Times New Roman"/><w:sz w:val="24"/><w:sz-cs w:val="24"/></w:rPr></w:pPr><w:r wsp:rsidRPr="00C20652"><w:rPr><w:rFonts w:ascii="Times New Roman" w:fareast="Times New Roman" w:h-ansi="Times New Roman"/><wx:font wx:val="Times New Roman"/><w:sz w:val="24"/><w:sz-cs w:val="24"/></w:rPr><w:t> </w:t></w:r></w:p></w:tc><w:tc><w:tcPr><w:tcW w:w="2435" w:type="dxa"/><w:tcBorders><w:bottom w:val="single" w:sz="4" wx:bdrwidth="10" w:space="0" w:color="auto"/></w:tcBorders><w:noWrap/><w:vAlign w:val="bottom"/></w:tcPr><w:p wsp:rsidR="000B002A" wsp:rsidRPr="00C20652" wsp:rsidRDefault="000B002A" wsp:rsidP="000B002A"><w:pPr><w:spacing w:after="0" w:line="240" w:line-rule="auto"/><w:rPr><w:rFonts w:ascii="Times New Roman" w:fareast="Times New Roman" w:h-ansi="Times New Roman"/><wx:font wx:val="Times New Roman"/><w:sz w:val="24"/><w:sz-cs w:val="24"/></w:rPr></w:pPr></w:p></w:tc><w:tc><w:tcPr><w:tcW w:w="1542" w:type="dxa"/><w:gridSpan w:val="2"/><w:tcBorders><w:bottom w:val="single" w:sz="4" wx:bdrwidth="10" w:space="0" w:color="auto"/></w:tcBorders><w:noWrap/><w:vAlign w:val="bottom"/></w:tcPr><w:p wsp:rsidR="000B002A" wsp:rsidRPr="00C20652" wsp:rsidRDefault="000B002A" wsp:rsidP="000B002A"><w:pPr><w:spacing w:after="0" w:line="240" w:line-rule="auto"/><w:rPr><w:rFonts w:ascii="Times New Roman" w:fareast="Times New Roman" w:h-ansi="Times New Roman"/><wx:font wx:val="Times New Roman"/><w:sz w:val="24"/><w:sz-cs w:val="24"/></w:rPr></w:pPr></w:p></w:tc><w:tc><w:tcPr><w:tcW w:w="352" w:type="dxa"/><w:tcBorders><w:bottom w:val="single" w:sz="4" wx:bdrwidth="10" w:space="0" w:color="auto"/></w:tcBorders><w:noWrap/><w:vAlign w:val="bottom"/></w:tcPr><w:p wsp:rsidR="000B002A" wsp:rsidRPr="00C20652" wsp:rsidRDefault="000B002A" wsp:rsidP="000B002A"><w:pPr><w:spacing w:after="0" w:line="240" w:line-rule="auto"/><w:rPr><w:rFonts w:ascii="Times New Roman" w:fareast="Times New Roman" w:h-ansi="Times New Roman"/><wx:font wx:val="Times New Roman"/><w:sz w:val="24"/><w:sz-cs w:val="24"/></w:rPr></w:pPr></w:p></w:tc><w:tc><w:tcPr><w:tcW w:w="3888" w:type="dxa"/><w:gridSpan w:val="2"/><w:tcBorders><w:bottom w:val="single" w:sz="4" wx:bdrwidth="10" w:space="0" w:color="auto"/></w:tcBorders><w:noWrap/><w:vAlign w:val="bottom"/></w:tcPr><w:p wsp:rsidR="000B002A" wsp:rsidRPr="00C20652" wsp:rsidRDefault="000B002A" wsp:rsidP="000B002A"><w:pPr><w:spacing w:after="0" w:line="240" w:line-rule="auto"/><w:rPr><w:rFonts w:ascii="Times New Roman" w:fareast="Times New Roman" w:h-ansi="Times New Roman"/><wx:font wx:val="Times New Roman"/><w:sz w:val="24"/><w:sz-cs w:val="24"/></w:rPr></w:pPr></w:p></w:tc><w:tc><w:tcPr><w:tcW w:w="283" w:type="dxa"/><w:noWrap/><w:vAlign w:val="bottom"/></w:tcPr><w:p wsp:rsidR="000B002A" wsp:rsidRPr="00C20652" wsp:rsidRDefault="000B002A" wsp:rsidP="000B002A"><w:pPr><w:spacing w:after="0" w:line="240" w:line-rule="auto"/><w:jc w:val="center"/><w:rPr><w:rFonts w:ascii="Times New Roman" w:fareast="Times New Roman" w:h-ansi="Times New Roman"/><wx:font wx:val="Times New Roman"/><w:sz w:val="24"/><w:sz-cs w:val="24"/></w:rPr></w:pPr></w:p></w:tc></w:tr><w:tr wsp:rsidR="000B002A" wsp:rsidRPr="00C20652" wsp:rsidTr="005273AB"><w:trPr><w:gridAfter w:val="1"/><w:wAfter w:w="283" w:type="dxa"/><w:trHeight w:val="454"/></w:trPr><w:tc><w:tcPr><w:tcW w:w="851" w:type="dxa"/><w:vmerge w:val="restart"/><w:tcBorders><w:top w:val="single" w:sz="4" wx:bdrwidth="10" w:space="0" w:color="auto"/><w:left w:val="single" w:sz="4" wx:bdrwidth="10" w:space="0" w:color="auto"/><w:bottom w:val="single" w:sz="4" wx:bdrwidth="10" w:space="0" w:color="auto"/><w:right w:val="single" w:sz="4" wx:bdrwidth="10" w:space="0" w:color="auto"/></w:tcBorders><w:shd w:val="clear" w:color="auto" w:fill="EDEDED"/><w:noWrap/><w:vAlign w:val="center"/></w:tcPr><w:p wsp:rsidR="000B002A" wsp:rsidRPr="00C20652" wsp:rsidRDefault="000B002A" wsp:rsidP="002227ED"><w:pPr><w:spacing w:after="0" w:line="240" w:line-rule="auto"/><w:jc w:val="center"/><w:rPr><w:rFonts w:ascii="Times New Roman" w:fareast="Times New Roman" w:h-ansi="Times New Roman"/><wx:font wx:val="Times New Roman"/><w:b/><w:b-cs/><w:sz w:val="24"/><w:sz-cs w:val="24"/></w:rPr></w:pPr><w:r wsp:rsidRPr="00C20652"><w:rPr><w:rFonts w:ascii="Times New Roman" w:fareast="Times New Roman" w:h-ansi="Times New Roman"/><wx:font wx:val="Times New Roman"/><w:b/><w:b-cs/><w:sz w:val="24"/><w:sz-cs w:val="24"/></w:rPr><w:t>STT</w:t></w:r></w:p></w:tc><w:tc><w:tcPr><w:tcW w:w="4819" w:type="dxa"/><w:gridSpan w:val="5"/><w:vmerge w:val="restart"/><w:tcBorders><w:top w:val="single" w:sz="4" wx:bdrwidth="10" w:space="0" w:color="auto"/><w:left w:val="single" w:sz="4" wx:bdrwidth="10" w:space="0" w:color="auto"/><w:bottom w:val="single" w:sz="4" wx:bdrwidth="10" w:space="0" w:color="auto"/><w:right w:val="single" w:sz="4" wx:bdrwidth="10" w:space="0" w:color="auto"/></w:tcBorders><w:shd w:val="clear" w:color="auto" w:fill="EDEDED"/><w:noWrap/><w:vAlign w:val="center"/></w:tcPr><w:p wsp:rsidR="000B002A" wsp:rsidRPr="00C20652" wsp:rsidRDefault="008A2C61" wsp:rsidP="002227ED"><w:pPr><w:spacing w:after="0" w:line="240" w:line-rule="auto"/><w:jc w:val="center"/><w:rPr><w:rFonts w:ascii="Times New Roman" w:fareast="Times New Roman" w:h-ansi="Times New Roman"/><wx:font wx:val="Times New Roman"/><w:b/><w:b-cs/><w:sz w:val="24"/><w:sz-cs w:val="24"/></w:rPr></w:pPr><w:r><w:rPr><w:rFonts w:ascii="Times New Roman" w:fareast="Times New Roman" w:h-ansi="Times New Roman"/><wx:font wx:val="Times New Roman"/><w:b/><w:b-cs/><w:sz w:val="24"/><w:sz-cs w:val="24"/></w:rPr><w:t>Tên tài liệu</w:t></w:r></w:p></w:tc><w:tc><w:tcPr><w:tcW w:w="4253" w:type="dxa"/><w:gridSpan w:val="4"/><w:tcBorders><w:top w:val="single" w:sz="4" wx:bdrwidth="10" w:space="0" w:color="auto"/><w:left w:val="single" w:sz="4" wx:bdrwidth="10" w:space="0" w:color="auto"/><w:bottom w:val="single" w:sz="4" wx:bdrwidth="10" w:space="0" w:color="auto"/><w:right w:val="single" w:sz="4" wx:bdrwidth="10" w:space="0" w:color="auto"/></w:tcBorders><w:shd w:val="clear" w:color="auto" w:fill="EDEDED"/><w:noWrap/><w:vAlign w:val="center"/></w:tcPr><w:p wsp:rsidR="000B002A" wsp:rsidRPr="00C20652" wsp:rsidRDefault="008A2C61" wsp:rsidP="002227ED"><w:pPr><w:spacing w:after="0" w:line="240" w:line-rule="auto"/><w:jc w:val="center"/><w:rPr><w:rFonts w:ascii="Times New Roman" w:fareast="Times New Roman" w:h-ansi="Times New Roman"/><wx:font wx:val="Times New Roman"/><w:b/><w:b-cs/><w:sz w:val="24"/><w:sz-cs w:val="24"/></w:rPr></w:pPr><w:r><w:rPr><w:rFonts w:ascii="Times New Roman" w:fareast="Times New Roman" w:h-ansi="Times New Roman"/><wx:font wx:val="Times New Roman"/><w:b/><w:b-cs/><w:sz w:val="24"/><w:sz-cs w:val="24"/></w:rPr><w:t>Tài liệu</w:t></w:r></w:p></w:tc></w:tr><w:tr wsp:rsidR="000B002A" wsp:rsidRPr="00C20652" wsp:rsidTr="005273AB"><w:trPr><w:gridAfter w:val="1"/><w:wAfter w:w="283" w:type="dxa"/><w:trHeight w:val="454"/></w:trPr><w:tc><w:tcPr><w:tcW w:w="851" w:type="dxa"/><w:vmerge/><w:tcBorders><w:top w:val="single" w:sz="4" wx:bdrwidth="10" w:space="0" w:color="auto"/><w:left w:val="single" w:sz="4" wx:bdrwidth="10" w:space="0" w:color="auto"/><w:bottom w:val="single" w:sz="4" wx:bdrwidth="10" w:space="0" w:color="auto"/><w:right w:val="single" w:sz="4" wx:bdrwidth="10" w:space="0" w:color="auto"/></w:tcBorders><w:shd w:val="clear" w:color="auto" w:fill="EDEDED"/><w:vAlign w:val="center"/></w:tcPr><w:p wsp:rsidR="000B002A" wsp:rsidRPr="00C20652" wsp:rsidRDefault="000B002A" wsp:rsidP="002227ED"><w:pPr><w:spacing w:after="0" w:line="240" w:line-rule="auto"/><w:jc w:val="center"/><w:rPr><w:rFonts w:ascii="Times New Roman" w:fareast="Times New Roman" w:h-ansi="Times New Roman"/><wx:font wx:val="Times New Roman"/><w:b/><w:b-cs/><w:sz w:val="24"/><w:sz-cs w:val="24"/></w:rPr></w:pPr></w:p></w:tc><w:tc><w:tcPr><w:tcW w:w="4819" w:type="dxa"/><w:gridSpan w:val="5"/><w:vmerge/><w:tcBorders><w:top w:val="single" w:sz="4" wx:bdrwidth="10" w:space="0" w:color="auto"/><w:left w:val="single" w:sz="4" wx:bdrwidth="10" w:space="0" w:color="auto"/><w:bottom w:val="single" w:sz="4" wx:bdrwidth="10" w:space="0" w:color="auto"/><w:right w:val="single" w:sz="4" wx:bdrwidth="10" w:space="0" w:color="auto"/></w:tcBorders><w:shd w:val="clear" w:color="auto" w:fill="EDEDED"/><w:vAlign w:val="center"/></w:tcPr><w:p wsp:rsidR="000B002A" wsp:rsidRPr="00C20652" wsp:rsidRDefault="000B002A" wsp:rsidP="002227ED"><w:pPr><w:spacing w:after="0" w:line="240" w:line-rule="auto"/><w:jc w:val="center"/><w:rPr><w:rFonts w:ascii="Times New Roman" w:fareast="Times New Roman" w:h-ansi="Times New Roman"/><wx:font wx:val="Times New Roman"/><w:b/><w:b-cs/><w:sz w:val="24"/><w:sz-cs w:val="24"/></w:rPr></w:pPr></w:p></w:tc><w:tc><w:tcPr><w:tcW w:w="1985" w:type="dxa"/><w:gridSpan w:val="3"/><w:tcBorders><w:top w:val="single" w:sz="4" wx:bdrwidth="10" w:space="0" w:color="auto"/><w:left w:val="single" w:sz="4" wx:bdrwidth="10" w:space="0" w:color="auto"/><w:bottom w:val="single" w:sz="4" wx:bdrwidth="10" w:space="0" w:color="auto"/><w:right w:val="single" w:sz="4" wx:bdrwidth="10" w:space="0" w:color="auto"/></w:tcBorders><w:shd w:val="clear" w:color="auto" w:fill="EDEDED"/><w:noWrap/><w:vAlign w:val="center"/></w:tcPr><w:p wsp:rsidR="000B002A" wsp:rsidRPr="00C20652" wsp:rsidRDefault="00B26AC1" wsp:rsidP="002227ED"><w:pPr><w:spacing w:after="0" w:line="240" w:line-rule="auto"/><w:jc w:val="center"/><w:rPr><w:rFonts w:ascii="Times New Roman" w:fareast="Times New Roman" w:h-ansi="Times New Roman"/><wx:font wx:val="Times New Roman"/><w:b/><w:b-cs/><w:sz w:val="24"/><w:sz-cs w:val="24"/></w:rPr></w:pPr><w:r wsp:rsidRPr="00C20652"><w:rPr><w:rFonts w:ascii="Times New Roman" w:fareast="Times New Roman" w:h-ansi="Times New Roman"/><wx:font wx:val="Times New Roman"/><w:b/><w:b-cs/><w:sz w:val="24"/><w:sz-cs w:val="24"/></w:rPr><w:t>Ngày cung cấp</w:t></w:r></w:p></w:tc><w:tc><w:tcPr><w:tcW w:w="2268" w:type="dxa"/><w:tcBorders><w:top w:val="single" w:sz="4" wx:bdrwidth="10" w:space="0" w:color="auto"/><w:left w:val="single" w:sz="4" wx:bdrwidth="10" w:space="0" w:color="auto"/><w:bottom w:val="single" w:sz="4" wx:bdrwidth="10" w:space="0" w:color="auto"/><w:right w:val="single" w:sz="4" wx:bdrwidth="10" w:space="0" w:color="auto"/></w:tcBorders><w:shd w:val="clear" w:color="auto" w:fill="EDEDED"/><w:noWrap/><w:vAlign w:val="center"/></w:tcPr><w:p wsp:rsidR="000B002A" wsp:rsidRPr="00C20652" wsp:rsidRDefault="00B26AC1" wsp:rsidP="002227ED"><w:pPr><w:spacing w:after="0" w:line="240" w:line-rule="auto"/><w:jc w:val="center"/><w:rPr><w:rFonts w:ascii="Times New Roman" w:fareast="Times New Roman" w:h-ansi="Times New Roman"/><wx:font wx:val="Times New Roman"/><w:b/><w:b-cs/><w:sz w:val="24"/><w:sz-cs w:val="24"/></w:rPr></w:pPr><w:r wsp:rsidRPr="00C20652"><w:rPr><w:rFonts w:ascii="Times New Roman" w:fareast="Times New Roman" w:h-ansi="Times New Roman"/><wx:font wx:val="Times New Roman"/><w:b/><w:b-cs/><w:sz w:val="24"/><w:sz-cs w:val="24"/></w:rPr><w:t>Trạng thái bổ sung</w:t></w:r></w:p></w:tc></w:tr><w:tr wsp:rsidR="000B002A" wsp:rsidRPr="00C20652" wsp:rsidTr="005273AB"><w:trPr><w:gridAfter w:val="1"/><w:wAfter w:w="283" w:type="dxa"/><w:trHeight w:val="454"/></w:trPr><w:tc><w:tcPr><w:tcW w:w="851" w:type="dxa"/><w:tcBorders><w:top w:val="single" w:sz="4" wx:bdrwidth="10" w:space="0" w:color="auto"/><w:left w:val="single" w:sz="4" wx:bdrwidth="10" w:space="0" w:color="auto"/><w:bottom w:val="single" w:sz="4" wx:bdrwidth="10" w:space="0" w:color="auto"/><w:right w:val="single" w:sz="4" wx:bdrwidth="10" w:space="0" w:color="auto"/></w:tcBorders><w:noWrap/><w:vAlign w:val="center"/></w:tcPr><w:p wsp:rsidR="000B002A" wsp:rsidRPr="00C20652" wsp:rsidRDefault="00E84323" wsp:rsidP="002227ED"><w:pPr><w:spacing w:after="0" w:line="240" w:line-rule="auto"/><w:jc w:val="center"/><w:rPr><w:rFonts w:ascii="Times New Roman" w:fareast="Times New Roman" w:h-ansi="Times New Roman"/><wx:font wx:val="Times New Roman"/><w:sz w:val="24"/><w:sz-cs w:val="24"/></w:rPr></w:pPr><w:r wsp:rsidRPr="00C20652"><w:rPr><w:rFonts w:ascii="Times New Roman" w:fareast="Times New Roman" w:h-ansi="Times New Roman"/><wx:font wx:val="Times New Roman"/><w:sz w:val="24"/><w:sz-cs w:val="24"/></w:rPr><w:fldChar w:fldCharType="begin"/></w:r><w:r wsp:rsidR="00243AF5" wsp:rsidRPr="00C20652"><w:rPr><w:rFonts w:ascii="Times New Roman" w:fareast="Times New Roman" w:h-ansi="Times New Roman"/><wx:font wx:val="Times New Roman"/><w:sz w:val="24"/><w:sz-cs w:val="24"/></w:rPr><w:instrText> MERGEFIELD  ISTT </w:instrText></w:r><w:r wsp:rsidRPr="00C20652"><w:rPr><w:rFonts w:ascii="Times New Roman" w:fareast="Times New Roman" w:h-ansi="Times New Roman"/><wx:font wx:val="Times New Roman"/><w:sz w:val="24"/><w:sz-cs w:val="24"/></w:rPr><w:fldChar w:fldCharType="separate"/></w:r><w:r wsp:rsidR="00243AF5" wsp:rsidRPr="00C20652"><w:rPr><w:rFonts w:ascii="Times New Roman" w:fareast="Times New Roman" w:h-ansi="Times New Roman"/><wx:font wx:val="Times New Roman"/><w:noProof/><w:sz w:val="24"/><w:sz-cs w:val="24"/></w:rPr><w:t>«ISTT»</w:t></w:r><w:r wsp:rsidRPr="00C20652"><w:rPr><w:rFonts w:ascii="Times New Roman" w:fareast="Times New Roman" w:h-ansi="Times New Roman"/><wx:font wx:val="Times New Roman"/><w:sz w:val="24"/><w:sz-cs w:val="24"/></w:rPr><w:fldChar w:fldCharType="end"/></w:r></w:p></w:tc><w:tc><w:tcPr><w:tcW w:w="4819" w:type="dxa"/><w:gridSpan w:val="5"/><w:tcBorders><w:top w:val="single" w:sz="4" wx:bdrwidth="10" w:space="0" w:color="auto"/><w:left w:val="single" w:sz="4" wx:bdrwidth="10" w:space="0" w:color="auto"/><w:bottom w:val="single" w:sz="4" wx:bdrwidth="10" w:space="0" w:color="auto"/><w:right w:val="single" w:sz="4" wx:bdrwidth="10" w:space="0" w:color="auto"/></w:tcBorders><w:noWrap/><w:vAlign w:val="center"/></w:tcPr><w:p wsp:rsidR="000B002A" wsp:rsidRPr="00C20652" wsp:rsidRDefault="00E84323" wsp:rsidP="002227ED"><w:pPr><w:spacing w:after="0" w:line="240" w:line-rule="auto"/><w:rPr><w:rFonts w:ascii="Times New Roman" w:fareast="Times New Roman" w:h-ansi="Times New Roman"/><wx:font wx:val="Times New Roman"/><w:sz w:val="24"/><w:sz-cs w:val="24"/></w:rPr></w:pPr><w:r wsp:rsidRPr="00C20652"><w:rPr><w:rFonts w:ascii="Times New Roman" w:fareast="Times New Roman" w:h-ansi="Times New Roman"/><wx:font wx:val="Times New Roman"/><w:sz w:val="24"/><w:sz-cs w:val="24"/></w:rPr><w:fldChar w:fldCharType="begin"/></w:r><w:r wsp:rsidR="00730B04" wsp:rsidRPr="00C20652"><w:rPr><w:rFonts w:ascii="Times New Roman" w:fareast="Times New Roman" w:h-ansi="Times New Roman"/><wx:font wx:val="Times New Roman"/><w:sz w:val="24"/><w:sz-cs w:val="24"/></w:rPr><w:instrText> MERGEFIELD  ITEN </w:instrText></w:r><w:r wsp:rsidRPr="00C20652"><w:rPr><w:rFonts w:ascii="Times New Roman" w:fareast="Times New Roman" w:h-ansi="Times New Roman"/><wx:font wx:val="Times New Roman"/><w:sz w:val="24"/><w:sz-cs w:val="24"/></w:rPr><w:fldChar w:fldCharType="separate"/></w:r><w:r wsp:rsidR="00730B04" wsp:rsidRPr="00C20652"><w:rPr><w:rFonts w:ascii="Times New Roman" w:fareast="Times New Roman" w:h-ansi="Times New Roman"/><wx:font wx:val="Times New Roman"/><w:noProof/><w:sz w:val="24"/><w:sz-cs w:val="24"/></w:rPr><w:t>«ITEN»</w:t></w:r><w:r wsp:rsidRPr="00C20652"><w:rPr><w:rFonts w:ascii="Times New Roman" w:fareast="Times New Roman" w:h-ansi="Times New Roman"/><wx:font wx:val="Times New Roman"/><w:sz w:val="24"/><w:sz-cs w:val="24"/></w:rPr><w:fldChar w:fldCharType="end"/></w:r></w:p></w:tc><w:tc><w:tcPr><w:tcW w:w="1985" w:type="dxa"/><w:gridSpan w:val="3"/><w:tcBorders><w:top w:val="single" w:sz="4" wx:bdrwidth="10" w:space="0" w:color="auto"/><w:left w:val="single" w:sz="4" wx:bdrwidth="10" w:space="0" w:color="auto"/><w:bottom w:val="single" w:sz="4" wx:bdrwidth="10" w:space="0" w:color="auto"/><w:right w:val="single" w:sz="4" wx:bdrwidth="10" w:space="0" w:color="auto"/></w:tcBorders><w:noWrap/><w:vAlign w:val="center"/></w:tcPr><w:p wsp:rsidR="000B002A" wsp:rsidRPr="00C20652" wsp:rsidRDefault="00E84323" wsp:rsidP="002227ED"><w:pPr><w:spacing w:after="0" w:line="240" w:line-rule="auto"/><w:jc w:val="center"/><w:rPr><w:rFonts w:ascii="Times New Roman" w:fareast="Times New Roman" w:h-ansi="Times New Roman"/><wx:font wx:val="Times New Roman"/><w:sz w:val="24"/><w:sz-cs w:val="24"/></w:rPr></w:pPr><w:r wsp:rsidRPr="00C20652"><w:rPr><w:rFonts w:ascii="Times New Roman" w:fareast="Times New Roman" w:h-ansi="Times New Roman"/><wx:font wx:val="Times New Roman"/><w:sz w:val="24"/><w:sz-cs w:val="24"/></w:rPr><w:fldChar w:fldCharType="begin"/></w:r><w:r wsp:rsidR="00730B04" wsp:rsidRPr="00C20652"><w:rPr><w:rFonts w:ascii="Times New Roman" w:fareast="Times New Roman" w:h-ansi="Times New Roman"/><wx:font wx:val="Times New Roman"/><w:sz w:val="24"/><w:sz-cs w:val="24"/></w:rPr><w:instrText> MERGEFIELD  INGAY_BS </w:instrText></w:r><w:r wsp:rsidRPr="00C20652"><w:rPr><w:rFonts w:ascii="Times New Roman" w:fareast="Times New Roman" w:h-ansi="Times New Roman"/><wx:font wx:val="Times New Roman"/><w:sz w:val="24"/><w:sz-cs w:val="24"/></w:rPr><w:fldChar w:fldCharType="separate"/></w:r><w:r wsp:rsidR="00730B04" wsp:rsidRPr="00C20652"><w:rPr><w:rFonts w:ascii="Times New Roman" w:fareast="Times New Roman" w:h-ansi="Times New Roman"/><wx:font wx:val="Times New Roman"/><w:noProof/><w:sz w:val="24"/><w:sz-cs w:val="24"/></w:rPr><w:t>«INGAY_BS»</w:t></w:r><w:r wsp:rsidRPr="00C20652"><w:rPr><w:rFonts w:ascii="Times New Roman" w:fareast="Times New Roman" w:h-ansi="Times New Roman"/><wx:font wx:val="Times New Roman"/><w:sz w:val="24"/><w:sz-cs w:val="24"/></w:rPr><w:fldChar w:fldCharType="end"/></w:r></w:p></w:tc><w:tc><w:tcPr><w:tcW w:w="2268" w:type="dxa"/><w:tcBorders><w:top w:val="single" w:sz="4" wx:bdrwidth="10" w:space="0" w:color="auto"/><w:left w:val="single" w:sz="4" wx:bdrwidth="10" w:space="0" w:color="auto"/><w:bottom w:val="single" w:sz="4" wx:bdrwidth="10" w:space="0" w:color="auto"/><w:right w:val="single" w:sz="4" wx:bdrwidth="10" w:space="0" w:color="auto"/></w:tcBorders><w:noWrap/><w:vAlign w:val="center"/></w:tcPr><w:p wsp:rsidR="000B002A" wsp:rsidRPr="00C20652" wsp:rsidRDefault="00E84323" wsp:rsidP="002227ED"><w:pPr><w:spacing w:after="0" w:line="240" w:line-rule="auto"/><w:jc w:val="center"/><w:rPr><w:rFonts w:ascii="Times New Roman" w:fareast="Times New Roman" w:h-ansi="Times New Roman"/><wx:font wx:val="Times New Roman"/><w:sz w:val="24"/><w:sz-cs w:val="24"/></w:rPr></w:pPr><w:r><w:rPr><w:rFonts w:ascii="Times New Roman" w:fareast="Times New Roman" w:h-ansi="Times New Roman"/><wx:font wx:val="Times New Roman"/><w:sz w:val="24"/><w:sz-cs w:val="24"/></w:rPr><w:fldChar w:fldCharType="begin"/></w:r><w:r wsp:rsidR="00F77EB6"><w:rPr><w:rFonts w:ascii="Times New Roman" w:fareast="Times New Roman" w:h-ansi="Times New Roman"/><wx:font wx:val="Times New Roman"/><w:sz w:val="24"/><w:sz-cs w:val="24"/></w:rPr><w:instrText> MERGEFIELD  ITRANG_THAI </w:instrText></w:r><w:r><w:rPr><w:rFonts w:ascii="Times New Roman" w:fareast="Times New Roman" w:h-ansi="Times New Roman"/><wx:font wx:val="Times New Roman"/><w:sz w:val="24"/><w:sz-cs w:val="24"/></w:rPr><w:fldChar w:fldCharType="separate"/></w:r><w:r wsp:rsidR="00F77EB6"><w:rPr><w:rFonts w:ascii="Times New Roman" w:fareast="Times New Roman" w:h-ansi="Times New Roman"/><wx:font wx:val="Times New Roman"/><w:noProof/><w:sz w:val="24"/><w:sz-cs w:val="24"/></w:rPr><w:t>«ITRANG_THAI»</w:t></w:r><w:r><w:rPr><w:rFonts w:ascii="Times New Roman" w:fareast="Times New Roman" w:h-ansi="Times New Roman"/><wx:font wx:val="Times New Roman"/><w:sz w:val="24"/><w:sz-cs w:val="24"/></w:rPr><w:fldChar w:fldCharType="end"/></w:r><aml:annotation aml:id="1" w:type="Word.Bookmark.Start" w:name="IWMLRepeat"/><aml:annotation aml:id="1" w:type="Word.Bookmark.End"/></w:p></w:tc></w:tr></w:tbl><w:p wsp:rsidR="009940E5" wsp:rsidRDefault="009940E5" wsp:rsidP="008470AD"><w:pPr><w:spacing w:after="0" w:line="240" w:line-rule="auto"/><w:rPr><w:rFonts w:ascii="Times New Roman" w:fareast="Times New Roman" w:h-ansi="Times New Roman"/><wx:font wx:val="Times New Roman"/><w:i-cs/><w:sz w:val="24"/><w:sz-cs w:val="24"/></w:rPr></w:pPr></w:p><w:p wsp:rsidR="00855E11" wsp:rsidRPr="00C20652" wsp:rsidRDefault="008470AD" wsp:rsidP="002227ED"><w:pPr><w:spacing w:after="0"/><w:jc w:val="both"/><w:rPr><w:rFonts w:ascii="Times New Roman" w:fareast="Times New Roman" w:h-ansi="Times New Roman"/><wx:font wx:val="Times New Roman"/><w:i-cs/><w:sz w:val="24"/><w:sz-cs w:val="24"/></w:rPr></w:pPr><w:r wsp:rsidRPr="00C20652"><w:rPr><w:rFonts w:ascii="Times New Roman" w:fareast="Times New Roman" w:h-ansi="Times New Roman"/><wx:font wx:val="Times New Roman"/><w:i-cs/><w:sz w:val="24"/><w:sz-cs w:val="24"/></w:rPr><w:t>Vui lòng cung cấp những hồ sơ còn thiếu </w:t></w:r><w:r wsp:rsidR="0030498F" wsp:rsidRPr="00C20652"><w:rPr><w:rFonts w:ascii="Times New Roman" w:fareast="Times New Roman" w:h-ansi="Times New Roman"/><wx:font wx:val="Times New Roman"/><w:i-cs/><w:sz w:val="24"/><w:sz-cs w:val="24"/></w:rPr><w:t>cho đại diện </w:t></w:r><w:r wsp:rsidR="002227ED"><w:rPr><w:rFonts w:ascii="Times New Roman" w:fareast="Times New Roman" w:h-ansi="Times New Roman"/><wx:font wx:val="Times New Roman"/><w:i-cs/><w:sz w:val="24"/><w:sz-cs w:val="24"/></w:rPr><w:t>C</w:t></w:r><w:r wsp:rsidR="007E762D"><w:rPr><w:rFonts w:ascii="Times New Roman" w:fareast="Times New Roman" w:h-ansi="Times New Roman"/><wx:font wx:val="Times New Roman"/><w:i-cs/><w:sz w:val="24"/><w:sz-cs w:val="24"/></w:rPr><w:t>ông ty bảo hiểm</w:t></w:r><w:r wsp:rsidRPr="00C20652"><w:rPr><w:rFonts w:ascii="Times New Roman" w:fareast="Times New Roman" w:h-ansi="Times New Roman"/><wx:font wx:val="Times New Roman"/><w:i-cs/><w:sz w:val="24"/><w:sz-cs w:val="24"/></w:rPr><w:t> trong thời gian sớm nhất theo thông tin liên hệ dưới đây:</w:t></w:r></w:p><w:tbl><w:tblPr><w:tblW w:w="0" w:type="auto"/><w:tblInd w:w="-34" w:type="dxa"/><w:tblLook w:val="04A0"/></w:tblPr><w:tblGrid><w:gridCol w:w="1492"/><w:gridCol w:w="8680"/></w:tblGrid><w:tr wsp:rsidR="00E967DA" wsp:rsidRPr="00C20652" wsp:rsidTr="009B2E55"><w:tc><w:tcPr><w:tcW w:w="1492" w:type="dxa"/><w:shd w:val="clear" w:color="auto" w:fill="auto"/></w:tcPr><w:p wsp:rsidR="00AC163E" wsp:rsidRPr="00C20652" wsp:rsidRDefault="00AC163E" wsp:rsidP="002227ED"><w:pPr><w:spacing w:before="60" w:after="60"/><w:rPr><w:rFonts w:ascii="Times New Roman" w:fareast="Times New Roman" w:h-ansi="Times New Roman"/><wx:font wx:val="Times New Roman"/><w:i-cs/><w:sz w:val="24"/><w:sz-cs w:val="24"/></w:rPr></w:pPr><w:r wsp:rsidRPr="00C20652"><w:rPr><w:rFonts w:ascii="Times New Roman" w:fareast="Times New Roman" w:h-ansi="Times New Roman"/><wx:font wx:val="Times New Roman"/><w:i-cs/><w:sz w:val="24"/><w:sz-cs w:val="24"/></w:rPr><w:t>Họ và tên</w:t></w:r></w:p></w:tc><w:tc><w:tcPr><w:tcW w:w="8680" w:type="dxa"/><w:shd w:val="clear" w:color="auto" w:fill="auto"/></w:tcPr><w:p wsp:rsidR="00AC163E" wsp:rsidRPr="00C20652" wsp:rsidRDefault="00AC163E" wsp:rsidP="002227ED"><w:pPr><w:spacing w:before="60" w:after="60"/><w:rPr><w:rFonts w:ascii="Times New Roman" w:fareast="Times New Roman" w:h-ansi="Times New Roman"/><wx:font wx:val="Times New Roman"/><w:i-cs/><w:sz w:val="24"/><w:sz-cs w:val="24"/></w:rPr></w:pPr><w:r wsp:rsidRPr="00C20652"><w:rPr><w:rFonts w:ascii="Times New Roman" w:fareast="Times New Roman" w:h-ansi="Times New Roman"/><wx:font wx:val="Times New Roman"/><w:i-cs/><w:sz w:val="24"/><w:sz-cs w:val="24"/></w:rPr><w:t>: </w:t></w:r><w:r wsp:rsidR="00E84323" wsp:rsidRPr="00C20652"><w:rPr><w:rFonts w:ascii="Times New Roman" w:h-ansi="Times New Roman"/><wx:font wx:val="Times New Roman"/><w:sz w:val="24"/><w:sz-cs w:val="24"/></w:rPr><w:fldChar w:fldCharType="begin"/></w:r><w:r wsp:rsidR="00B26AC1" wsp:rsidRPr="00C20652"><w:rPr><w:rFonts w:ascii="Times New Roman" w:h-ansi="Times New Roman"/><wx:font wx:val="Times New Roman"/><w:sz w:val="24"/><w:sz-cs w:val="24"/></w:rPr><w:instrText> MERGEFIELD  JTEN </w:instrText></w:r><w:r wsp:rsidR="00E84323" wsp:rsidRPr="00C20652"><w:rPr><w:rFonts w:ascii="Times New Roman" w:h-ansi="Times New Roman"/><wx:font wx:val="Times New Roman"/><w:sz w:val="24"/><w:sz-cs w:val="24"/></w:rPr><w:fldChar w:fldCharType="separate"/></w:r><w:r wsp:rsidR="00B26AC1" wsp:rsidRPr="00C20652"><w:rPr><w:rFonts w:ascii="Times New Roman" w:h-ansi="Times New Roman"/><wx:font wx:val="Times New Roman"/><w:noProof/><w:sz w:val="24"/><w:sz-cs w:val="24"/></w:rPr><w:t>«JTEN»</w:t></w:r><w:r wsp:rsidR="00E84323" wsp:rsidRPr="00C20652"><w:rPr><w:rFonts w:ascii="Times New Roman" w:h-ansi="Times New Roman"/><wx:font wx:val="Times New Roman"/><w:sz w:val="24"/><w:sz-cs w:val="24"/></w:rPr><w:fldChar w:fldCharType="end"/></w:r></w:p></w:tc></w:tr><w:tr wsp:rsidR="00E967DA" wsp:rsidRPr="00C20652" wsp:rsidTr="009B2E55"><w:tc><w:tcPr><w:tcW w:w="1492" w:type="dxa"/><w:shd w:val="clear" w:color="auto" w:fill="auto"/></w:tcPr><w:p wsp:rsidR="00AC163E" wsp:rsidRPr="00C20652" wsp:rsidRDefault="00AC163E" wsp:rsidP="002227ED"><w:pPr><w:spacing w:before="60" w:after="60"/><w:rPr><w:rFonts w:ascii="Times New Roman" w:fareast="Times New Roman" w:h-ansi="Times New Roman"/><wx:font wx:val="Times New Roman"/><w:i-cs/><w:sz w:val="24"/><w:sz-cs w:val="24"/></w:rPr></w:pPr><w:r wsp:rsidRPr="00C20652"><w:rPr><w:rFonts w:ascii="Times New Roman" w:fareast="Times New Roman" w:h-ansi="Times New Roman"/><wx:font wx:val="Times New Roman"/><w:i-cs/><w:sz w:val="24"/><w:sz-cs w:val="24"/></w:rPr><w:t>Số điện thoại</w:t></w:r></w:p></w:tc><w:tc><w:tcPr><w:tcW w:w="8680" w:type="dxa"/><w:shd w:val="clear" w:color="auto" w:fill="auto"/></w:tcPr><w:p wsp:rsidR="00AC163E" wsp:rsidRPr="00C20652" wsp:rsidRDefault="00B26AC1" wsp:rsidP="002227ED"><w:pPr><w:tabs><w:tab w:val="left" w:pos="7185"/></w:tabs><w:spacing w:before="60" w:after="60"/><w:rPr><w:rFonts w:ascii="Times New Roman" w:fareast="Times New Roman" w:h-ansi="Times New Roman"/><wx:font wx:val="Times New Roman"/><w:i-cs/><w:sz w:val="24"/><w:sz-cs w:val="24"/></w:rPr></w:pPr><w:r wsp:rsidRPr="00C20652"><w:rPr><w:rFonts w:ascii="Times New Roman" w:fareast="Times New Roman" w:h-ansi="Times New Roman"/><wx:font wx:val="Times New Roman"/><w:i-cs/><w:sz w:val="24"/><w:sz-cs w:val="24"/></w:rPr><w:t>: </w:t></w:r><w:r wsp:rsidR="00E84323" wsp:rsidRPr="00C20652"><w:rPr><w:rFonts w:ascii="Times New Roman" w:h-ansi="Times New Roman"/><wx:font wx:val="Times New Roman"/><w:sz w:val="24"/><w:sz-cs w:val="24"/></w:rPr><w:fldChar w:fldCharType="begin"/></w:r><w:r wsp:rsidRPr="00C20652"><w:rPr><w:rFonts w:ascii="Times New Roman" w:h-ansi="Times New Roman"/><wx:font wx:val="Times New Roman"/><w:sz w:val="24"/><w:sz-cs w:val="24"/></w:rPr><w:instrText> MERGEFIELD  JDTHOAI </w:instrText></w:r><w:r wsp:rsidR="00E84323" wsp:rsidRPr="00C20652"><w:rPr><w:rFonts w:ascii="Times New Roman" w:h-ansi="Times New Roman"/><wx:font wx:val="Times New Roman"/><w:sz w:val="24"/><w:sz-cs w:val="24"/></w:rPr><w:fldChar w:fldCharType="separate"/></w:r><w:r wsp:rsidRPr="00C20652"><w:rPr><w:rFonts w:ascii="Times New Roman" w:h-ansi="Times New Roman"/><wx:font wx:val="Times New Roman"/><w:noProof/><w:sz w:val="24"/><w:sz-cs w:val="24"/></w:rPr><w:t>«JDTHOAI»</w:t></w:r><w:r wsp:rsidR="00E84323" wsp:rsidRPr="00C20652"><w:rPr><w:rFonts w:ascii="Times New Roman" w:h-ansi="Times New Roman"/><wx:font wx:val="Times New Roman"/><w:sz w:val="24"/><w:sz-cs w:val="24"/></w:rPr><w:fldChar w:fldCharType="end"/></w:r></w:p></w:tc></w:tr><w:tr wsp:rsidR="00E967DA" wsp:rsidRPr="00C20652" wsp:rsidTr="009B2E55"><w:tc><w:tcPr><w:tcW w:w="1492" w:type="dxa"/><w:shd w:val="clear" w:color="auto" w:fill="auto"/></w:tcPr><w:p wsp:rsidR="00AC163E" wsp:rsidRPr="00C20652" wsp:rsidRDefault="00AC163E" wsp:rsidP="002227ED"><w:pPr><w:spacing w:before="60" w:after="60"/><w:rPr><w:rFonts w:ascii="Times New Roman" w:fareast="Times New Roman" w:h-ansi="Times New Roman"/><wx:font wx:val="Times New Roman"/><w:i-cs/><w:sz w:val="24"/><w:sz-cs w:val="24"/></w:rPr></w:pPr><w:r wsp:rsidRPr="00C20652"><w:rPr><w:rFonts w:ascii="Times New Roman" w:fareast="Times New Roman" w:h-ansi="Times New Roman"/><wx:font wx:val="Times New Roman"/><w:i-cs/><w:sz w:val="24"/><w:sz-cs w:val="24"/></w:rPr><w:t>E-mail</w:t></w:r></w:p></w:tc><w:tc><w:tcPr><w:tcW w:w="8680" w:type="dxa"/><w:shd w:val="clear" w:color="auto" w:fill="auto"/></w:tcPr><w:p wsp:rsidR="00AC163E" wsp:rsidRPr="00C20652" wsp:rsidRDefault="00AC163E" wsp:rsidP="002227ED"><w:pPr><w:tabs><w:tab w:val="left" w:pos="7080"/></w:tabs><w:spacing w:before="60" w:after="60"/><w:rPr><w:rFonts w:ascii="Times New Roman" w:fareast="Times New Roman" w:h-ansi="Times New Roman"/><wx:font wx:val="Times New Roman"/><w:i-cs/><w:sz w:val="24"/><w:sz-cs w:val="24"/></w:rPr></w:pPr><w:r wsp:rsidRPr="00C20652"><w:rPr><w:rFonts w:ascii="Times New Roman" w:fareast="Times New Roman" w:h-ansi="Times New Roman"/><wx:font wx:val="Times New Roman"/><w:i-cs/><w:sz w:val="24"/><w:sz-cs w:val="24"/></w:rPr><w:t>: </w:t></w:r><w:r wsp:rsidR="00E84323" wsp:rsidRPr="00C20652"><w:rPr><w:rFonts w:ascii="Times New Roman" w:h-ansi="Times New Roman"/><wx:font wx:val="Times New Roman"/><w:sz w:val="24"/><w:sz-cs w:val="24"/></w:rPr><w:fldChar w:fldCharType="begin"/></w:r><w:r wsp:rsidR="00B26AC1" wsp:rsidRPr="00C20652"><w:rPr><w:rFonts w:ascii="Times New Roman" w:h-ansi="Times New Roman"/><wx:font wx:val="Times New Roman"/><w:sz w:val="24"/><w:sz-cs w:val="24"/></w:rPr><w:instrText> MERGEFIELD  JEMAIL </w:instrText></w:r><w:r wsp:rsidR="00E84323" wsp:rsidRPr="00C20652"><w:rPr><w:rFonts w:ascii="Times New Roman" w:h-ansi="Times New Roman"/><wx:font wx:val="Times New Roman"/><w:sz w:val="24"/><w:sz-cs w:val="24"/></w:rPr><w:fldChar w:fldCharType="separate"/></w:r><w:r wsp:rsidR="00B26AC1" wsp:rsidRPr="00C20652"><w:rPr><w:rFonts w:ascii="Times New Roman" w:h-ansi="Times New Roman"/><wx:font wx:val="Times New Roman"/><w:noProof/><w:sz w:val="24"/><w:sz-cs w:val="24"/></w:rPr><w:t>«JEMAIL»</w:t></w:r><w:r wsp:rsidR="00E84323" wsp:rsidRPr="00C20652"><w:rPr><w:rFonts w:ascii="Times New Roman" w:h-ansi="Times New Roman"/><wx:font wx:val="Times New Roman"/><w:sz w:val="24"/><w:sz-cs w:val="24"/></w:rPr><w:fldChar w:fldCharType="end"/></w:r></w:p></w:tc></w:tr><w:tr wsp:rsidR="00E967DA" wsp:rsidRPr="00C20652" wsp:rsidTr="009B2E55"><w:tc><w:tcPr><w:tcW w:w="1492" w:type="dxa"/><w:shd w:val="clear" w:color="auto" w:fill="auto"/></w:tcPr><w:p wsp:rsidR="00AC163E" wsp:rsidRPr="00C20652" wsp:rsidRDefault="00AC163E" wsp:rsidP="002227ED"><w:pPr><w:spacing w:before="60" w:after="60"/><w:rPr><w:rFonts w:ascii="Times New Roman" w:fareast="Times New Roman" w:h-ansi="Times New Roman"/><wx:font wx:val="Times New Roman"/><w:i-cs/><w:sz w:val="24"/><w:sz-cs w:val="24"/></w:rPr></w:pPr><w:r wsp:rsidRPr="00C20652"><w:rPr><w:rFonts w:ascii="Times New Roman" w:fareast="Times New Roman" w:h-ansi="Times New Roman"/><wx:font wx:val="Times New Roman"/><w:i-cs/><w:sz w:val="24"/><w:sz-cs w:val="24"/></w:rPr><w:t>Địa chỉ</w:t></w:r></w:p></w:tc><w:tc><w:tcPr><w:tcW w:w="8680" w:type="dxa"/><w:shd w:val="clear" w:color="auto" w:fill="auto"/></w:tcPr><w:p wsp:rsidR="00AC163E" wsp:rsidRPr="00C20652" wsp:rsidRDefault="00AC163E" wsp:rsidP="002227ED"><w:pPr><w:tabs><w:tab w:val="left" w:pos="6765"/></w:tabs><w:spacing w:before="60" w:after="60"/><w:rPr><w:rFonts w:ascii="Times New Roman" w:fareast="Times New Roman" w:h-ansi="Times New Roman"/><wx:font wx:val="Times New Roman"/><w:i-cs/><w:sz w:val="24"/><w:sz-cs w:val="24"/></w:rPr></w:pPr><w:r wsp:rsidRPr="00C20652"><w:rPr><w:rFonts w:ascii="Times New Roman" w:fareast="Times New Roman" w:h-ansi="Times New Roman"/><wx:font wx:val="Times New Roman"/><w:i-cs/><w:sz w:val="24"/><w:sz-cs w:val="24"/></w:rPr><w:t>: </w:t></w:r><w:r wsp:rsidR="00E84323" wsp:rsidRPr="00C20652"><w:rPr><w:rFonts w:ascii="Times New Roman" w:h-ansi="Times New Roman"/><wx:font wx:val="Times New Roman"/><w:sz w:val="24"/><w:sz-cs w:val="24"/></w:rPr><w:fldChar w:fldCharType="begin"/></w:r><w:r wsp:rsidR="00642886" wsp:rsidRPr="00C20652"><w:rPr><w:rFonts w:ascii="Times New Roman" w:h-ansi="Times New Roman"/><wx:font wx:val="Times New Roman"/><w:sz w:val="24"/><w:sz-cs w:val="24"/></w:rPr><w:instrText> MERGEFIELD  BDCHI </w:instrText></w:r><w:r wsp:rsidR="00E84323" wsp:rsidRPr="00C20652"><w:rPr><w:rFonts w:ascii="Times New Roman" w:h-ansi="Times New Roman"/><wx:font wx:val="Times New Roman"/><w:sz w:val="24"/><w:sz-cs w:val="24"/></w:rPr><w:fldChar w:fldCharType="separate"/></w:r><w:r wsp:rsidR="002009D0" wsp:rsidRPr="00C20652"><w:rPr><w:rFonts w:ascii="Times New Roman" w:h-ansi="Times New Roman"/><wx:font wx:val="Times New Roman"/><w:noProof/><w:sz w:val="24"/><w:sz-cs w:val="24"/></w:rPr><w:t>«BDCHI»</w:t></w:r><w:r wsp:rsidR="00E84323" wsp:rsidRPr="00C20652"><w:rPr><w:rFonts w:ascii="Times New Roman" w:h-ansi="Times New Roman"/><wx:font wx:val="Times New Roman"/><w:sz w:val="24"/><w:sz-cs w:val="24"/></w:rPr><w:fldChar w:fldCharType="end"/></w:r></w:p></w:tc></w:tr></w:tbl><w:p wsp:rsidR="00E967DA" wsp:rsidRPr="00C20652" wsp:rsidRDefault="00E967DA" wsp:rsidP="00E967DA"><w:pPr><w:spacing w:after="0"/><w:rPr><w:rFonts w:ascii="Times New Roman" w:h-ansi="Times New Roman"/><wx:font wx:val="Times New Roman"/><w:vanish/><w:sz w:val="24"/><w:sz-cs w:val="24"/></w:rPr></w:pPr></w:p><w:tbl><w:tblPr><w:tblW w:w="0" w:type="auto"/><w:tblLook w:val="04A0"/></w:tblPr><w:tblGrid><w:gridCol w:w="4786"/><w:gridCol w:w="5352"/></w:tblGrid><w:tr wsp:rsidR="008470AD" wsp:rsidRPr="00C20652" wsp:rsidTr="007E762D"><w:trPr><w:trHeight w:val="454"/></w:trPr><w:tc><w:tcPr><w:tcW w:w="4786" w:type="dxa"/><w:shd w:val="clear" w:color="auto" w:fill="auto"/></w:tcPr><w:p wsp:rsidR="008470AD" wsp:rsidRPr="00C20652" wsp:rsidRDefault="008470AD" wsp:rsidP="007E762D"><w:pPr><w:tabs><w:tab w:val="left" w:pos="4142"/></w:tabs><w:spacing w:after="0" w:line="240" w:line-rule="auto"/><w:jc w:val="center"/><w:rPr><w:rFonts w:ascii="Times New Roman" w:h-ansi="Times New Roman"/><wx:font wx:val="Times New Roman"/><w:sz w:val="24"/><w:sz-cs w:val="24"/></w:rPr></w:pPr></w:p></w:tc><w:tc><w:tcPr><w:tcW w:w="5352" w:type="dxa"/><w:shd w:val="clear" w:color="auto" w:fill="auto"/><w:vAlign w:val="center"/></w:tcPr><w:p wsp:rsidR="008470AD" wsp:rsidRPr="007E762D" wsp:rsidRDefault="00B26AC1" wsp:rsidP="007E762D"><w:pPr><w:spacing w:after="0" w:line="240" w:line-rule="auto"/><w:jc w:val="center"/><w:rPr><w:rFonts w:ascii="Times New Roman" w:fareast="Times New Roman" w:h-ansi="Times New Roman"/><wx:font wx:val="Times New Roman"/><w:b/><w:b-cs/><w:i/><w:sz w:val="24"/><w:sz-cs w:val="24"/></w:rPr></w:pPr><w:r wsp:rsidRPr="007E762D"><w:rPr><w:rFonts w:ascii="Times New Roman" w:fareast="Times New Roman" w:h-ansi="Times New Roman"/><wx:font wx:val="Times New Roman"/><w:i/><w:sz w:val="24"/><w:sz-cs w:val="24"/></w:rPr><w:t>Ngày </w:t></w:r><w:r wsp:rsidR="00E84323" wsp:rsidRPr="007E762D"><w:rPr><w:rFonts w:ascii="Times New Roman" w:fareast="Times New Roman" w:h-ansi="Times New Roman"/><wx:font wx:val="Times New Roman"/><w:i/><w:sz w:val="24"/><w:sz-cs w:val="24"/></w:rPr><w:fldChar w:fldCharType="begin"/></w:r><w:r wsp:rsidR="00326EC5" wsp:rsidRPr="007E762D"><w:rPr><w:rFonts w:ascii="Times New Roman" w:fareast="Times New Roman" w:h-ansi="Times New Roman"/><wx:font wx:val="Times New Roman"/><w:i/><w:sz w:val="24"/><w:sz-cs w:val="24"/></w:rPr><w:instrText> MERGEFIELD  BNGAY </w:instrText></w:r><w:r wsp:rsidR="00E84323" wsp:rsidRPr="007E762D"><w:rPr><w:rFonts w:ascii="Times New Roman" w:fareast="Times New Roman" w:h-ansi="Times New Roman"/><wx:font wx:val="Times New Roman"/><w:i/><w:sz w:val="24"/><w:sz-cs w:val="24"/></w:rPr><w:fldChar w:fldCharType="separate"/></w:r><w:r wsp:rsidR="00326EC5" wsp:rsidRPr="007E762D"><w:rPr><w:rFonts w:ascii="Times New Roman" w:fareast="Times New Roman" w:h-ansi="Times New Roman"/><wx:font wx:val="Times New Roman"/><w:i/><w:noProof/><w:sz w:val="24"/><w:sz-cs w:val="24"/></w:rPr><w:t>«BNGAY»</w:t></w:r><w:r wsp:rsidR="00E84323" wsp:rsidRPr="007E762D"><w:rPr><w:rFonts w:ascii="Times New Roman" w:fareast="Times New Roman" w:h-ansi="Times New Roman"/><wx:font wx:val="Times New Roman"/><w:i/><w:sz w:val="24"/><w:sz-cs w:val="24"/></w:rPr><w:fldChar w:fldCharType="end"/></w:r><w:r wsp:rsidR="008470AD" wsp:rsidRPr="007E762D"><w:rPr><w:rFonts w:ascii="Times New Roman" w:fareast="Times New Roman" w:h-ansi="Times New Roman"/><wx:font wx:val="Times New Roman"/><w:i/><w:sz w:val="24"/><w:sz-cs w:val="24"/></w:rPr><w:t> tháng</w:t></w:r><w:r wsp:rsidRPr="007E762D"><w:rPr><w:rFonts w:ascii="Times New Roman" w:fareast="Times New Roman" w:h-ansi="Times New Roman"/><wx:font wx:val="Times New Roman"/><w:i/><w:sz w:val="24"/><w:sz-cs w:val="24"/></w:rPr><w:t> </w:t></w:r><w:r wsp:rsidR="00E84323" wsp:rsidRPr="007E762D"><w:rPr><w:rFonts w:ascii="Times New Roman" w:fareast="Times New Roman" w:h-ansi="Times New Roman"/><wx:font wx:val="Times New Roman"/><w:i/><w:sz w:val="24"/><w:sz-cs w:val="24"/></w:rPr><w:fldChar w:fldCharType="begin"/></w:r><w:r wsp:rsidR="00326EC5" wsp:rsidRPr="007E762D"><w:rPr><w:rFonts w:ascii="Times New Roman" w:fareast="Times New Roman" w:h-ansi="Times New Roman"/><wx:font wx:val="Times New Roman"/><w:i/><w:sz w:val="24"/><w:sz-cs w:val="24"/></w:rPr><w:instrText> MERGEFIELD  BTHANG </w:instrText></w:r><w:r wsp:rsidR="00E84323" wsp:rsidRPr="007E762D"><w:rPr><w:rFonts w:ascii="Times New Roman" w:fareast="Times New Roman" w:h-ansi="Times New Roman"/><wx:font wx:val="Times New Roman"/><w:i/><w:sz w:val="24"/><w:sz-cs w:val="24"/></w:rPr><w:fldChar w:fldCharType="separate"/></w:r><w:r wsp:rsidR="00326EC5" wsp:rsidRPr="007E762D"><w:rPr><w:rFonts w:ascii="Times New Roman" w:fareast="Times New Roman" w:h-ansi="Times New Roman"/><wx:font wx:val="Times New Roman"/><w:i/><w:noProof/><w:sz w:val="24"/><w:sz-cs w:val="24"/></w:rPr><w:t>«BTHANG»</w:t></w:r><w:r wsp:rsidR="00E84323" wsp:rsidRPr="007E762D"><w:rPr><w:rFonts w:ascii="Times New Roman" w:fareast="Times New Roman" w:h-ansi="Times New Roman"/><wx:font wx:val="Times New Roman"/><w:i/><w:sz w:val="24"/><w:sz-cs w:val="24"/></w:rPr><w:fldChar w:fldCharType="end"/></w:r><w:r wsp:rsidRPr="007E762D"><w:rPr><w:rFonts w:ascii="Times New Roman" w:fareast="Times New Roman" w:h-ansi="Times New Roman"/><wx:font wx:val="Times New Roman"/><w:i/><w:sz w:val="24"/><w:sz-cs w:val="24"/></w:rPr><w:t> năm </w:t></w:r><w:r wsp:rsidR="00E84323" wsp:rsidRPr="007E762D"><w:rPr><w:rFonts w:ascii="Times New Roman" w:fareast="Times New Roman" w:h-ansi="Times New Roman"/><wx:font wx:val="Times New Roman"/><w:i/><w:sz w:val="24"/><w:sz-cs w:val="24"/></w:rPr><w:fldChar w:fldCharType="begin"/></w:r><w:r wsp:rsidR="005D2866" wsp:rsidRPr="007E762D"><w:rPr><w:rFonts w:ascii="Times New Roman" w:fareast="Times New Roman" w:h-ansi="Times New Roman"/><wx:font wx:val="Times New Roman"/><w:i/><w:sz w:val="24"/><w:sz-cs w:val="24"/></w:rPr><w:instrText> MERGEFIELD  BNAM </w:instrText></w:r><w:r wsp:rsidR="00E84323" wsp:rsidRPr="007E762D"><w:rPr><w:rFonts w:ascii="Times New Roman" w:fareast="Times New Roman" w:h-ansi="Times New Roman"/><wx:font wx:val="Times New Roman"/><w:i/><w:sz w:val="24"/><w:sz-cs w:val="24"/></w:rPr><w:fldChar w:fldCharType="separate"/></w:r><w:r wsp:rsidR="005D2866" wsp:rsidRPr="007E762D"><w:rPr><w:rFonts w:ascii="Times New Roman" w:fareast="Times New Roman" w:h-ansi="Times New Roman"/><wx:font wx:val="Times New Roman"/><w:i/><w:noProof/><w:sz w:val="24"/><w:sz-cs w:val="24"/></w:rPr><w:t>«BNAM»</w:t></w:r><w:r wsp:rsidR="00E84323" wsp:rsidRPr="007E762D"><w:rPr><w:rFonts w:ascii="Times New Roman" w:fareast="Times New Roman" w:h-ansi="Times New Roman"/><wx:font wx:val="Times New Roman"/><w:i/><w:sz w:val="24"/><w:sz-cs w:val="24"/></w:rPr><w:fldChar w:fldCharType="end"/></w:r></w:p></w:tc></w:tr><w:tr wsp:rsidR="008470AD" wsp:rsidRPr="00C20652" wsp:rsidTr="007E762D"><w:trPr><w:trHeight w:val="342"/></w:trPr><w:tc><w:tcPr><w:tcW w:w="4786" w:type="dxa"/><w:shd w:val="clear" w:color="auto" w:fill="auto"/></w:tcPr><w:p wsp:rsidR="008470AD" wsp:rsidRDefault="008470AD" wsp:rsidP="007B4C70"><w:pPr><w:tabs><w:tab w:val="left" w:pos="4142"/></w:tabs><w:spacing w:before="60" w:after="60" w:line="240" w:line-rule="auto"/><w:jc w:val="center"/><w:rPr><w:rFonts w:ascii="Times New Roman" w:h-ansi="Times New Roman"/><wx:font wx:val="Times New Roman"/><w:b/><w:sz w:val="24"/><w:sz-cs w:val="24"/></w:rPr></w:pPr><w:r wsp:rsidRPr="00C20652"><w:rPr><w:rFonts w:ascii="Times New Roman" w:h-ansi="Times New Roman"/><wx:font wx:val="Times New Roman"/><w:b/><w:sz w:val="24"/><w:sz-cs w:val="24"/></w:rPr><w:t>ĐẠI DIỆN CHỦ XE</w:t></w:r></w:p><w:p wsp:rsidR="007E762D" wsp:rsidRPr="007E762D" wsp:rsidRDefault="007E762D" wsp:rsidP="007B4C70"><w:pPr><w:tabs><w:tab w:val="left" w:pos="4142"/></w:tabs><w:spacing w:before="60" w:after="60" w:line="240" w:line-rule="auto"/><w:jc w:val="center"/><w:rPr><w:rFonts w:ascii="Times New Roman" w:h-ansi="Times New Roman"/><wx:font wx:val="Times New Roman"/><w:b-cs/><w:i/><w:i-cs/><w:sz w:val="24"/><w:sz-cs w:val="24"/></w:rPr></w:pPr><w:r wsp:rsidRPr="007E762D"><w:rPr><w:rFonts w:ascii="Times New Roman" w:h-ansi="Times New Roman"/><wx:font wx:val="Times New Roman"/><w:b-cs/><w:i/><w:i-cs/><w:sz w:val="24"/><w:sz-cs w:val="24"/></w:rPr><w:t>(Kí, ghi rõ họ tên)</w:t></w:r></w:p></w:tc><w:tc><w:tcPr><w:tcW w:w="5352" w:type="dxa"/><w:shd w:val="clear" w:color="auto" w:fill="auto"/></w:tcPr><w:p wsp:rsidR="00FD5511" wsp:rsidRDefault="008470AD" wsp:rsidP="00D7615A"><w:pPr><w:tabs><w:tab w:val="left" w:pos="4142"/></w:tabs><w:spacing w:before="60" w:after="60" w:line="240" w:line-rule="auto"/><w:jc w:val="center"/><w:rPr><w:rFonts w:ascii="Times New Roman" w:fareast="Times New Roman" w:h-ansi="Times New Roman"/><wx:font wx:val="Times New Roman"/><w:b/><w:b-cs/><w:sz w:val="24"/><w:sz-cs w:val="24"/></w:rPr></w:pPr><w:r wsp:rsidRPr="00C20652"><w:rPr><w:rFonts w:ascii="Times New Roman" w:fareast="Times New Roman" w:h-ansi="Times New Roman"/><wx:font wx:val="Times New Roman"/><w:b/><w:b-cs/><w:sz w:val="24"/><w:sz-cs w:val="24"/></w:rPr><w:t>ĐẠI DIỆN BẢO HIỂM </w:t></w:r></w:p><w:p wsp:rsidR="007E762D" wsp:rsidRPr="007E762D" wsp:rsidRDefault="007E762D" wsp:rsidP="00D7615A"><w:pPr><w:tabs><w:tab w:val="left" w:pos="4142"/></w:tabs><w:spacing w:before="60" w:after="60" w:line="240" w:line-rule="auto"/><w:jc w:val="center"/><w:rPr><w:rFonts w:ascii="Times New Roman" w:h-ansi="Times New Roman"/><wx:font wx:val="Times New Roman"/><w:i/><w:i-cs/><w:sz w:val="24"/><w:sz-cs w:val="24"/></w:rPr></w:pPr><w:r wsp:rsidRPr="007E762D"><w:rPr><w:rFonts w:ascii="Times New Roman" w:h-ansi="Times New Roman"/><wx:font wx:val="Times New Roman"/><w:i/><w:i-cs/><w:sz w:val="24"/><w:sz-cs w:val="24"/></w:rPr><w:t>(Kí, ghi rõ họ tên)</w:t></w:r></w:p></w:tc></w:tr></w:tbl><w:p wsp:rsidR="007B4C70" wsp:rsidRDefault="007B4C70" wsp:rsidP="00F53F01"><w:pPr><w:tabs><w:tab w:val="left" w:pos="4142"/></w:tabs><w:rPr><w:rFonts w:ascii="Times New Roman" w:h-ansi="Times New Roman"/><wx:font wx:val="Times New Roman"/><w:sz w:val="20"/><w:sz-cs w:val="20"/></w:rPr></w:pPr></w:p><w:p wsp:rsidR="002B5BFB" wsp:rsidRDefault="002B5BFB" wsp:rsidP="00F53F01"><w:pPr><w:tabs><w:tab w:val="left" w:pos="4142"/></w:tabs><w:rPr><w:rFonts w:ascii="Times New Roman" w:h-ansi="Times New Roman"/><wx:font wx:val="Times New Roman"/><w:color w:val="FFFFFF"/><w:sz w:val="26"/><w:sz-cs w:val="26"/></w:rPr></w:pPr></w:p><w:p wsp:rsidR="00FD5511" wsp:rsidRDefault="00FD5511" wsp:rsidP="00F53F01"><w:pPr><w:tabs><w:tab w:val="left" w:pos="4142"/></w:tabs><w:rPr><w:rFonts w:ascii="Times New Roman" w:h-ansi="Times New Roman"/><wx:font wx:val="Times New Roman"/><w:sz w:val="20"/><w:sz-cs w:val="20"/></w:rPr></w:pPr></w:p><w:p wsp:rsidR="002B5BFB" wsp:rsidRDefault="002B5BFB" wsp:rsidP="00F53F01"><w:pPr><w:tabs><w:tab w:val="left" w:pos="4142"/></w:tabs><w:rPr><w:rFonts w:ascii="Times New Roman" w:h-ansi="Times New Roman"/><wx:font wx:val="Times New Roman"/><w:sz w:val="20"/><w:sz-cs w:val="20"/></w:rPr></w:pPr></w:p><w:sectPr wsp:rsidR="002B5BFB" wsp:rsidSect="00490B2A"><w:ftr w:type="odd"><w:p wsp:rsidR="007B4C70" wsp:rsidRDefault="007B4C70"><w:pPr><w:pStyle w:val="Footer"/></w:pPr></w:p><w:p wsp:rsidR="00E352A4" wsp:rsidRPr="00081F96" wsp:rsidRDefault="00E352A4" wsp:rsidP="00E352A4"><w:pPr><w:pStyle w:val="Footer"/><w:jc w:val="right"/><w:rPr><w:rFonts w:ascii="Times New Roman" w:h-ansi="Times New Roman"/><wx:font wx:val="Times New Roman"/><w:sz w:val="18"/><w:sz-cs w:val="18"/></w:rPr></w:pPr></w:p></w:ftr><w:pgSz w:w="11909" w:h="16834" w:code="9"/><w:pgMar w:top="720" w:right="994" w:bottom="288" w:left="993" w:header="144" w:footer="144" w:gutter="0"/><w:cols w:space="720"/><w:docGrid w:line-pitch="360"/></w:sectPr></wx:sect></w:body></w:wordDocument>